FFT_WIP/FFT/fft_512.v

module fft_512(clk, reset, xr_in, xi_in, fft_valid, fftr, ffti);

/*****************************************************************************
 *                             Port Declarations                             *
 *****************************************************************************/

input wire clk;
input wire reset;
input wire signed [23:0] xr_in, xi_in;
output reg fft_valid;
output reg signed [23:0] fftr, ffti;

/*****************************************************************************
 *                 Internal wires and registers Declarations                 *
 *****************************************************************************/
 
localparam N = 512;    // Number of points
localparam ldN = 9;    // Log_2(N)

// FSM states
localparam start=0, load=1, calc=2, update=3, reverse=4, done=5;
reg [2:0] s;
 
reg [7:0]  w;      
reg [9:0]  i1, i2; 
reg [9:0]  gcount; 
reg [10:0] k1, k2; 
reg [3:0]  stage;  
reg [9:0]  dw;     
reg [10:0] count; 
wire [9:0] rcount;

(* ramstyle = "M10K" *) reg signed [23:0] xr[511:0];
(* ramstyle = "M10K" *) reg signed [23:0] xi[511:0];

reg signed [31:0] tr, ti;
reg signed [31:0] cos_tr, sin_ti, cos_ti, sin_tr;
  
reg signed [15:0] cos_rom [0:255];
reg signed [15:0] sin_rom [0:255];

initial begin
	$readmemh("cos_lut.txt", cos_rom);
	$readmemh("sin_lut.txt", sin_rom);
end

// Combinational bit-reversal logic
assign rcount = {count[0], count[1], count[2], count[3], count[4], 
                 count[5], count[6], count[7], count[8]};
                 
/*****************************************************************************
 *                         Finite State Machine(s)                           *
 *****************************************************************************/
always @(posedge clk or posedge reset) begin : States
	if (reset) begin
		s <= start; 
      count <= 0;
      gcount <= 0; 
      stage <= 1; 
      i1 <= 0; 
      i2 <= N/2; 
      k1 <= N;
      k2 <= N/2; 
      dw <= 1; 
      w <= 0;
      fft_valid <= 0;
      fftr <= 0; 
      ffti <= 0; 
	end else begin 
		case (s)
			start: begin
				s <= load; 
				count <= 0; 
            w <= 0;
            gcount <= 0; 
            stage <= 1; 
            i1 <= 0; 
            i2 <= N/2; 
            k1 <= N;
            k2 <= N/2; 
            dw <= 1; 
            fft_valid <= 0; 
			end

         load: begin
				xr[count] <= xr_in; 
            xi[count] <= xi_in;
            if (count == N-1) begin
               s <= calc;
               count <= 0;
            end else begin
               count <= count + 1;
            end
			end

			calc: begin
            // Butterfly
            tr = xr[i1] - xr[i2];
            xr[i1] <= xr[i1] + xr[i2];
            ti = xi[i1] - xi[i2];
            xi[i1] <= xi[i1] + xi[i2];

            cos_tr = cos_rom[w] * tr; 
            sin_ti = sin_rom[w] * ti;
            xr[i2] <= (cos_tr + sin_ti) >>> 15;

            cos_ti = cos_rom[w] * ti; 
            sin_tr = sin_rom[w] * tr;
            xi[i2] <= (cos_ti - sin_tr) >>> 15;
                        
            s <= update;
			end

         update: begin
            if (i1 + k1 < N) begin
               i1 <= i1 + k1;
               i2 <= (i1 + k1) + k2;
               s <= calc;
            end else if (gcount + 1 < k2) begin
               gcount <= gcount + 1;
               i1 <= gcount + 1;
               i2 <= gcount + 1 + k2;
               w <= w + dw;
               s <= calc;
            end else if (stage < ldN) begin
               stage <= stage + 1;
               k1 <= k2;
               k2 <= k2 / 2;
               dw <= dw * 2;
               w <= 0;
               gcount <= 0;
               i1 <= 0;
               i2 <= k2 / 2;
               s <= calc;
            end else begin
               count <= 0;
               s <= reverse;
            end
			end

         reverse: begin
				fft_valid <= 1;
            fftr <= xr[rcount]; 
            ffti <= xi[rcount];
            if (count == N-1) begin
               s <= done;
            end else begin
               count <= count + 1;
            end
         end

         done: begin
				fft_valid <= 0;
				s <= start;
         end
		endcase
	end
end
endmodule

FFT_WIP/test_verilog/testbench.sv
`timescale 1ns/1ps

module fft_512_tb;

    // Parameters
    localparam N = 512;
    localparam CLK_PERIOD = 10; 
    localparam real PI = 3.141592653589;

    // DUT Signals
    reg clk;
    reg reset;
    reg signed [23:0] xr_in, xi_in;
    wire fft_valid;
    wire signed [23:0] fftr, ffti;

    // Testbench internal variables
    integer i;
    real amplitude = 100.0; 
    real cycles = 10.0;      // We want a peak at Index 10

    // Instantiate the FFT Module
    fft_512 dut (
        .clk(clk),
        .reset(reset),
        .xr_in(xr_in),
        .xi_in(xi_in),
        .fft_valid(fft_valid),
        .fftr(fftr),
        .ffti(ffti)
    );

    // Clock Generation
    initial clk = 0;
    always #(CLK_PERIOD/2) clk = ~clk;

    // Main Test Sequence
    initial begin
        // Initialize
        reset = 1;
        xr_in = 17'sd0;
        xi_in = 17'sd0;
        
        // Hold reset
        repeat(10) @(posedge clk);
        reset = 0;
        @(posedge clk);

        // --- STEP 1: LOAD PHASE ---
        $display("Status: Loading 10-cycle sine wave into FFT...");
        for (i = 0; i < N; i = i + 1) begin
            // Generate sine wave: A * sin(2 * pi * f * n / N)
            xr_in <= $rtoi(amplitude * $sin(2.0 * PI * cycles * i / N));
            xi_in <= 17'sd0; 
            @(posedge clk);
        end
        
        // Clear inputs after loading
        xr_in <= 17'sd0;
        xi_in <= 17'sd0;
        $display("Status: Load complete. Processing...");

        // --- STEP 2: CALCULATION PHASE ---
        // Wait for the module to finish computing
        wait(fft_valid == 1'b1);
        $display("Status: FFT Valid! Resulting Bins:");
        $display("---------------------------------------");

        // --- STEP 3: OUTPUT PHASE ---
        for (i = 0; i < N; i = i + 1) begin
            // In a 512-point FFT with 10 cycles, 
            // the peaks will be at Bin 10 and Bin 502 (N - 10)
            $display("Bin %4d | Real: %d | Imag: %d", i, fftr, ffti);
            @(posedge clk);
        end

        $display("---------------------------------------");
        $display("Simulation Finished.");
        $finish;
    end

    // Waveform Dump for GTKWave or Vivado
    initial begin
        $dumpfile("fft_512_test.vcd");
        $dumpvars(0, fft_512_tb);
    end

endmodule

FFT_WIP/test_verilog/fft_512_test.vcd
$date
	Wed Mar 04 10:57:25 2026
$end
$version
	Icarus Verilog
$end
$timescale
	1ps
$end
$scope module fft_512_tb $end
$var wire 24 ! fftr [23:0] $end
$var wire 24 " ffti [23:0] $end
$var wire 1 # fft_valid $end
$var parameter 32 $ CLK_PERIOD $end
$var parameter 32 % N $end
$var real 1 & PI $end
$var reg 1 ' clk $end
$var reg 1 ( reset $end
$var reg 24 ) xi_in [23:0] $end
$var reg 24 * xr_in [23:0] $end
$var real 1 + amplitude $end
$var real 1 , cycles $end
$var integer 32 - i [31:0] $end
$scope module dut $end
$var wire 1 ' clk $end
$var wire 1 ( reset $end
$var wire 24 . xi_in [23:0] $end
$var wire 24 / xr_in [23:0] $end
$var wire 10 0 rcount [9:0] $end
$var parameter 32 1 N $end
$var parameter 32 2 calc $end
$var parameter 32 3 done $end
$var parameter 32 4 ldN $end
$var parameter 32 5 load $end
$var parameter 32 6 reverse $end
$var parameter 32 7 start $end
$var parameter 32 8 update $end
$var reg 32 9 cos_ti [31:0] $end
$var reg 32 : cos_tr [31:0] $end
$var reg 11 ; count [10:0] $end
$var reg 10 < dw [9:0] $end
$var reg 1 # fft_valid $end
$var reg 24 = ffti [23:0] $end
$var reg 24 > fftr [23:0] $end
$var reg 10 ? gcount [9:0] $end
$var reg 10 @ i1 [9:0] $end
$var reg 10 A i2 [9:0] $end
$var reg 11 B k1 [10:0] $end
$var reg 11 C k2 [10:0] $end
$var reg 3 D s [2:0] $end
$var reg 32 E sin_ti [31:0] $end
$var reg 32 F sin_tr [31:0] $end
$var reg 4 G stage [3:0] $end
$var reg 32 H ti [31:0] $end
$var reg 32 I tr [31:0] $end
$var reg 8 J w [7:0] $end
$scope begin States $end
$upscope $end
$upscope $end
$upscope $end
$enddefinitions $end
$comment Show the parameter values. $end
$dumpall
b11 8
b0 7
b100 6
b1 5
b1001 4
b101 3
b10 2
b1000000000 1
r3.141592653589 &
b1000000000 %
b1010 $
$end
#0
$dumpvars
b0 J
bx I
bx H
b1 G
bx F
bx E
b0 D
b100000000 C
b1000000000 B
b100000000 A
b0 @
b0 ?
b0 >
b0 =
b1 <
b0 ;
bx :
bx 9
b0 0
b0 /
b0 .
bx -
r10 ,
r100 +
b0 *
b0 )
1(
0'
0#
b0 "
b0 !
$end
#5000
1'
#10000
0'
#15000
1'
#20000
0'
#25000
1'
#30000
0'
#35000
1'
#40000
0'
#45000
1'
#50000
0'
#55000
1'
#60000
0'
#65000
1'
#70000
0'
#75000
1'
#80000
0'
#85000
1'
#90000
0'
#95000
b1 D
0(
1'
#100000
0'
#105000
b100000000 0
b1 ;
b0 -
1'
#110000
0'
#115000
b10000000 0
b10 ;
b1100 *
b1100 /
b1 -
1'
#120000
0'
#125000
b110000000 0
b11 ;
b11000 *
b11000 /
b10 -
1'
#130000
0'
#135000
b1000000 0
b100 ;
b100011 *
b100011 /
b11 -
1'
#140000
0'
#145000
b101000000 0
b101 ;
b101111 *
b101111 /
b100 -
1'
#150000
0'
#155000
b11000000 0
b110 ;
b111001 *
b111001 /
b101 -
1'
#160000
0'
#165000
b111000000 0
b111 ;
b1000011 *
b1000011 /
b110 -
1'
#170000
0'
#175000
b100000 0
b1000 ;
b1001011 *
b1001011 /
b111 -
1'
#180000
0'
#185000
b100100000 0
b1001 ;
b1010011 *
b1010011 /
b1000 -
1'
#190000
0'
#195000
b10100000 0
b1010 ;
b1011001 *
b1011001 /
b1001 -
1'
#200000
0'
#205000
b110100000 0
b1011 ;
b1011110 *
b1011110 /
b1010 -
1'
#210000
0'
#215000
b1100000 0
b1100 ;
b1100001 *
b1100001 /
b1011 -
1'
#220000
0'
#225000
b101100000 0
b1101 ;
b1100011 *
b1100011 /
b1100 -
1'
#230000
0'
#235000
b11100000 0
b1110 ;
b1101 -
1'
#240000
0'
#245000
b111100000 0
b1111 ;
b1100010 *
b1100010 /
b1110 -
1'
#250000
0'
#255000
b10000 0
b10000 ;
b1100000 *
b1100000 /
b1111 -
1'
#260000
0'
#265000
b100010000 0
b10001 ;
b1011100 *
b1011100 /
b10000 -
1'
#270000
0'
#275000
b10010000 0
b10010 ;
b1010111 *
b1010111 /
b10001 -
1'
#280000
0'
#285000
b110010000 0
b10011 ;
b1010000 *
b1010000 /
b10010 -
1'
#290000
0'
#295000
b1010000 0
b10100 ;
b1001000 *
b1001000 /
b10011 -
1'
#300000
0'
#305000
b101010000 0
b10101 ;
b111111 *
b111111 /
b10100 -
1'
#310000
0'
#315000
b11010000 0
b10110 ;
b110101 *
b110101 /
b10101 -
1'
#320000
0'
#325000
b111010000 0
b10111 ;
b101010 *
b101010 /
b10110 -
1'
#330000
0'
#335000
b110000 0
b11000 ;
b11111 *
b11111 /
b10111 -
1'
#340000
0'
#345000
b100110000 0
b11001 ;
b10011 *
b10011 /
b11000 -
1'
#350000
0'
#355000
b10110000 0
b11010 ;
b111 *
b111 /
b11001 -
1'
#360000
0'
#365000
b110110000 0
b11011 ;
b111111111111111111111100 *
b111111111111111111111100 /
b11010 -
1'
#370000
0'
#375000
b1110000 0
b11100 ;
b111111111111111111101111 *
b111111111111111111101111 /
b11011 -
1'
#380000
0'
#385000
b101110000 0
b11101 ;
b111111111111111111100011 *
b111111111111111111100011 /
b11100 -
1'
#390000
0'
#395000
b11110000 0
b11110 ;
b111111111111111111011000 *
b111111111111111111011000 /
b11101 -
1'
#400000
0'
#405000
b111110000 0
b11111 ;
b111111111111111111001101 *
b111111111111111111001101 /
b11110 -
1'
#410000
0'
#415000
b1000 0
b100000 ;
b111111111111111111000011 *
b111111111111111111000011 /
b11111 -
1'
#420000
0'
#425000
b100001000 0
b100001 ;
b111111111111111110111010 *
b111111111111111110111010 /
b100000 -
1'
#430000
0'
#435000
b10001000 0
b100010 ;
b111111111111111110110010 *
b111111111111111110110010 /
b100001 -
1'
#440000
0'
#445000
b110001000 0
b100011 ;
b111111111111111110101011 *
b111111111111111110101011 /
b100010 -
1'
#450000
0'
#455000
b1001000 0
b100100 ;
b111111111111111110100101 *
b111111111111111110100101 /
b100011 -
1'
#460000
0'
#465000
b101001000 0
b100101 ;
b111111111111111110100001 *
b111111111111111110100001 /
b100100 -
1'
#470000
0'
#475000
b11001000 0
b100110 ;
b111111111111111110011110 *
b111111111111111110011110 /
b100101 -
1'
#480000
0'
#485000
b111001000 0
b100111 ;
b111111111111111110011101 *
b111111111111111110011101 /
b100110 -
1'
#490000
0'
#495000
b101000 0
b101000 ;
b100111 -
1'
#500000
0'
#505000
b100101000 0
b101001 ;
b111111111111111110011110 *
b111111111111111110011110 /
b101000 -
1'
#510000
0'
#515000
b10101000 0
b101010 ;
b111111111111111110100010 *
b111111111111111110100010 /
b101001 -
1'
#520000
0'
#525000
b110101000 0
b101011 ;
b111111111111111110100110 *
b111111111111111110100110 /
b101010 -
1'
#530000
0'
#535000
b1101000 0
b101100 ;
b111111111111111110101100 *
b111111111111111110101100 /
b101011 -
1'
#540000
0'
#545000
b101101000 0
b101101 ;
b111111111111111110110011 *
b111111111111111110110011 /
b101100 -
1'
#550000
0'
#555000
b11101000 0
b101110 ;
b111111111111111110111100 *
b111111111111111110111100 /
b101101 -
1'
#560000
0'
#565000
b111101000 0
b101111 ;
b111111111111111111000101 *
b111111111111111111000101 /
b101110 -
1'
#570000
0'
#575000
b11000 0
b110000 ;
b111111111111111111001111 *
b111111111111111111001111 /
b101111 -
1'
#580000
0'
#585000
b100011000 0
b110001 ;
b111111111111111111011010 *
b111111111111111111011010 /
b110000 -
1'
#590000
0'
#595000
b10011000 0
b110010 ;
b111111111111111111100110 *
b111111111111111111100110 /
b110001 -
1'
#600000
0'
#605000
b110011000 0
b110011 ;
b111111111111111111110010 *
b111111111111111111110010 /
b110010 -
1'
#610000
0'
#615000
b1011000 0
b110100 ;
b111111111111111111111110 *
b111111111111111111111110 /
b110011 -
1'
#620000
0'
#625000
b101011000 0
b110101 ;
b1001 *
b1001 /
b110100 -
1'
#630000
0'
#635000
b11011000 0
b110110 ;
b10101 *
b10101 /
b110101 -
1'
#640000
0'
#645000
b111011000 0
b110111 ;
b100001 *
b100001 /
b110110 -
1'
#650000
0'
#655000
b111000 0
b111000 ;
b101100 *
b101100 /
b110111 -
1'
#660000
0'
#665000
b100111000 0
b111001 ;
b110111 *
b110111 /
b111000 -
1'
#670000
0'
#675000
b10111000 0
b111010 ;
b1000001 *
b1000001 /
b111001 -
1'
#680000
0'
#685000
b110111000 0
b111011 ;
b1001010 *
b1001010 /
b111010 -
1'
#690000
0'
#695000
b1111000 0
b111100 ;
b1010001 *
b1010001 /
b111011 -
1'
#700000
0'
#705000
b101111000 0
b111101 ;
b1011000 *
b1011000 /
b111100 -
1'
#710000
0'
#715000
b11111000 0
b111110 ;
b1011101 *
b1011101 /
b111101 -
1'
#720000
0'
#725000
b111111000 0
b111111 ;
b1100001 *
b1100001 /
b111110 -
1'
#730000
0'
#735000
b100 0
b1000000 ;
b1100011 *
b1100011 /
b111111 -
1'
#740000
0'
#745000
b100000100 0
b1000001 ;
b1100100 *
b1100100 /
b1000000 -
1'
#750000
0'
#755000
b10000100 0
b1000010 ;
b1100011 *
b1100011 /
b1000001 -
1'
#760000
0'
#765000
b110000100 0
b1000011 ;
b1100001 *
b1100001 /
b1000010 -
1'
#770000
0'
#775000
b1000100 0
b1000100 ;
b1011101 *
b1011101 /
b1000011 -
1'
#780000
0'
#785000
b101000100 0
b1000101 ;
b1011000 *
b1011000 /
b1000100 -
1'
#790000
0'
#795000
b11000100 0
b1000110 ;
b1010001 *
b1010001 /
b1000101 -
1'
#800000
0'
#805000
b111000100 0
b1000111 ;
b1001010 *
b1001010 /
b1000110 -
1'
#810000
0'
#815000
b100100 0
b1001000 ;
b1000001 *
b1000001 /
b1000111 -
1'
#820000
0'
#825000
b100100100 0
b1001001 ;
b110111 *
b110111 /
b1001000 -
1'
#830000
0'
#835000
b10100100 0
b1001010 ;
b101100 *
b101100 /
b1001001 -
1'
#840000
0'
#845000
b110100100 0
b1001011 ;
b100001 *
b100001 /
b1001010 -
1'
#850000
0'
#855000
b1100100 0
b1001100 ;
b10101 *
b10101 /
b1001011 -
1'
#860000
0'
#865000
b101100100 0
b1001101 ;
b1001 *
b1001 /
b1001100 -
1'
#870000
0'
#875000
b11100100 0
b1001110 ;
b111111111111111111111110 *
b111111111111111111111110 /
b1001101 -
1'
#880000
0'
#885000
b111100100 0
b1001111 ;
b111111111111111111110010 *
b111111111111111111110010 /
b1001110 -
1'
#890000
0'
#895000
b10100 0
b1010000 ;
b111111111111111111100110 *
b111111111111111111100110 /
b1001111 -
1'
#900000
0'
#905000
b100010100 0
b1010001 ;
b111111111111111111011010 *
b111111111111111111011010 /
b1010000 -
1'
#910000
0'
#915000
b10010100 0
b1010010 ;
b111111111111111111001111 *
b111111111111111111001111 /
b1010001 -
1'
#920000
0'
#925000
b110010100 0
b1010011 ;
b111111111111111111000101 *
b111111111111111111000101 /
b1010010 -
1'
#930000
0'
#935000
b1010100 0
b1010100 ;
b111111111111111110111100 *
b111111111111111110111100 /
b1010011 -
1'
#940000
0'
#945000
b101010100 0
b1010101 ;
b111111111111111110110011 *
b111111111111111110110011 /
b1010100 -
1'
#950000
0'
#955000
b11010100 0
b1010110 ;
b111111111111111110101100 *
b111111111111111110101100 /
b1010101 -
1'
#960000
0'
#965000
b111010100 0
b1010111 ;
b111111111111111110100110 *
b111111111111111110100110 /
b1010110 -
1'
#970000
0'
#975000
b110100 0
b1011000 ;
b111111111111111110100010 *
b111111111111111110100010 /
b1010111 -
1'
#980000
0'
#985000
b100110100 0
b1011001 ;
b111111111111111110011110 *
b111111111111111110011110 /
b1011000 -
1'
#990000
0'
#995000
b10110100 0
b1011010 ;
b111111111111111110011101 *
b111111111111111110011101 /
b1011001 -
1'
#1000000
0'
#1005000
b110110100 0
b1011011 ;
b1011010 -
1'
#1010000
0'
#1015000
b1110100 0
b1011100 ;
b111111111111111110011110 *
b111111111111111110011110 /
b1011011 -
1'
#1020000
0'
#1025000
b101110100 0
b1011101 ;
b111111111111111110100001 *
b111111111111111110100001 /
b1011100 -
1'
#1030000
0'
#1035000
b11110100 0
b1011110 ;
b111111111111111110100101 *
b111111111111111110100101 /
b1011101 -
1'
#1040000
0'
#1045000
b111110100 0
b1011111 ;
b111111111111111110101011 *
b111111111111111110101011 /
b1011110 -
1'
#1050000
0'
#1055000
b1100 0
b1100000 ;
b111111111111111110110010 *
b111111111111111110110010 /
b1011111 -
1'
#1060000
0'
#1065000
b100001100 0
b1100001 ;
b111111111111111110111010 *
b111111111111111110111010 /
b1100000 -
1'
#1070000
0'
#1075000
b10001100 0
b1100010 ;
b111111111111111111000011 *
b111111111111111111000011 /
b1100001 -
1'
#1080000
0'
#1085000
b110001100 0
b1100011 ;
b111111111111111111001101 *
b111111111111111111001101 /
b1100010 -
1'
#1090000
0'
#1095000
b1001100 0
b1100100 ;
b111111111111111111011000 *
b111111111111111111011000 /
b1100011 -
1'
#1100000
0'
#1105000
b101001100 0
b1100101 ;
b111111111111111111100011 *
b111111111111111111100011 /
b1100100 -
1'
#1110000
0'
#1115000
b11001100 0
b1100110 ;
b111111111111111111101111 *
b111111111111111111101111 /
b1100101 -
1'
#1120000
0'
#1125000
b111001100 0
b1100111 ;
b111111111111111111111100 *
b111111111111111111111100 /
b1100110 -
1'
#1130000
0'
#1135000
b101100 0
b1101000 ;
b111 *
b111 /
b1100111 -
1'
#1140000
0'
#1145000
b100101100 0
b1101001 ;
b10011 *
b10011 /
b1101000 -
1'
#1150000
0'
#1155000
b10101100 0
b1101010 ;
b11111 *
b11111 /
b1101001 -
1'
#1160000
0'
#1165000
b110101100 0
b1101011 ;
b101010 *
b101010 /
b1101010 -
1'
#1170000
0'
#1175000
b1101100 0
b1101100 ;
b110101 *
b110101 /
b1101011 -
1'
#1180000
0'
#1185000
b101101100 0
b1101101 ;
b111111 *
b111111 /
b1101100 -
1'
#1190000
0'
#1195000
b11101100 0
b1101110 ;
b1001000 *
b1001000 /
b1101101 -
1'
#1200000
0'
#1205000
b111101100 0
b1101111 ;
b1010000 *
b1010000 /
b1101110 -
1'
#1210000
0'
#1215000
b11100 0
b1110000 ;
b1010111 *
b1010111 /
b1101111 -
1'
#1220000
0'
#1225000
b100011100 0
b1110001 ;
b1011100 *
b1011100 /
b1110000 -
1'
#1230000
0'
#1235000
b10011100 0
b1110010 ;
b1100000 *
b1100000 /
b1110001 -
1'
#1240000
0'
#1245000
b110011100 0
b1110011 ;
b1100010 *
b1100010 /
b1110010 -
1'
#1250000
0'
#1255000
b1011100 0
b1110100 ;
b1100011 *
b1100011 /
b1110011 -
1'
#1260000
0'
#1265000
b101011100 0
b1110101 ;
b1110100 -
1'
#1270000
0'
#1275000
b11011100 0
b1110110 ;
b1100001 *
b1100001 /
b1110101 -
1'
#1280000
0'
#1285000
b111011100 0
b1110111 ;
b1011110 *
b1011110 /
b1110110 -
1'
#1290000
0'
#1295000
b111100 0
b1111000 ;
b1011001 *
b1011001 /
b1110111 -
1'
#1300000
0'
#1305000
b100111100 0
b1111001 ;
b1010011 *
b1010011 /
b1111000 -
1'
#1310000
0'
#1315000
b10111100 0
b1111010 ;
b1001011 *
b1001011 /
b1111001 -
1'
#1320000
0'
#1325000
b110111100 0
b1111011 ;
b1000011 *
b1000011 /
b1111010 -
1'
#1330000
0'
#1335000
b1111100 0
b1111100 ;
b111001 *
b111001 /
b1111011 -
1'
#1340000
0'
#1345000
b101111100 0
b1111101 ;
b101111 *
b101111 /
b1111100 -
1'
#1350000
0'
#1355000
b11111100 0
b1111110 ;
b100011 *
b100011 /
b1111101 -
1'
#1360000
0'
#1365000
b111111100 0
b1111111 ;
b11000 *
b11000 /
b1111110 -
1'
#1370000
0'
#1375000
b10 0
b10000000 ;
b1100 *
b1100 /
b1111111 -
1'
#1380000
0'
#1385000
b100000010 0
b10000001 ;
b0 *
b0 /
b10000000 -
1'
#1390000
0'
#1395000
b10000010 0
b10000010 ;
b111111111111111111110100 *
b111111111111111111110100 /
b10000001 -
1'
#1400000
0'
#1405000
b110000010 0
b10000011 ;
b111111111111111111101000 *
b111111111111111111101000 /
b10000010 -
1'
#1410000
0'
#1415000
b1000010 0
b10000100 ;
b111111111111111111011101 *
b111111111111111111011101 /
b10000011 -
1'
#1420000
0'
#1425000
b101000010 0
b10000101 ;
b111111111111111111010001 *
b111111111111111111010001 /
b10000100 -
1'
#1430000
0'
#1435000
b11000010 0
b10000110 ;
b111111111111111111000111 *
b111111111111111111000111 /
b10000101 -
1'
#1440000
0'
#1445000
b111000010 0
b10000111 ;
b111111111111111110111101 *
b111111111111111110111101 /
b10000110 -
1'
#1450000
0'
#1455000
b100010 0
b10001000 ;
b111111111111111110110101 *
b111111111111111110110101 /
b10000111 -
1'
#1460000
0'
#1465000
b100100010 0
b10001001 ;
b111111111111111110101101 *
b111111111111111110101101 /
b10001000 -
1'
#1470000
0'
#1475000
b10100010 0
b10001010 ;
b111111111111111110100111 *
b111111111111111110100111 /
b10001001 -
1'
#1480000
0'
#1485000
b110100010 0
b10001011 ;
b111111111111111110100010 *
b111111111111111110100010 /
b10001010 -
1'
#1490000
0'
#1495000
b1100010 0
b10001100 ;
b111111111111111110011111 *
b111111111111111110011111 /
b10001011 -
1'
#1500000
0'
#1505000
b101100010 0
b10001101 ;
b111111111111111110011101 *
b111111111111111110011101 /
b10001100 -
1'
#1510000
0'
#1515000
b11100010 0
b10001110 ;
b10001101 -
1'
#1520000
0'
#1525000
b111100010 0
b10001111 ;
b111111111111111110011110 *
b111111111111111110011110 /
b10001110 -
1'
#1530000
0'
#1535000
b10010 0
b10010000 ;
b111111111111111110100000 *
b111111111111111110100000 /
b10001111 -
1'
#1540000
0'
#1545000
b100010010 0
b10010001 ;
b111111111111111110100100 *
b111111111111111110100100 /
b10010000 -
1'
#1550000
0'
#1555000
b10010010 0
b10010010 ;
b111111111111111110101001 *
b111111111111111110101001 /
b10010001 -
1'
#1560000
0'
#1565000
b110010010 0
b10010011 ;
b111111111111111110110000 *
b111111111111111110110000 /
b10010010 -
1'
#1570000
0'
#1575000
b1010010 0
b10010100 ;
b111111111111111110111000 *
b111111111111111110111000 /
b10010011 -
1'
#1580000
0'
#1585000
b101010010 0
b10010101 ;
b111111111111111111000001 *
b111111111111111111000001 /
b10010100 -
1'
#1590000
0'
#1595000
b11010010 0
b10010110 ;
b111111111111111111001011 *
b111111111111111111001011 /
b10010101 -
1'
#1600000
0'
#1605000
b111010010 0
b10010111 ;
b111111111111111111010110 *
b111111111111111111010110 /
b10010110 -
1'
#1610000
0'
#1615000
b110010 0
b10011000 ;
b111111111111111111100001 *
b111111111111111111100001 /
b10010111 -
1'
#1620000
0'
#1625000
b100110010 0
b10011001 ;
b111111111111111111101101 *
b111111111111111111101101 /
b10011000 -
1'
#1630000
0'
#1635000
b10110010 0
b10011010 ;
b111111111111111111111001 *
b111111111111111111111001 /
b10011001 -
1'
#1640000
0'
#1645000
b110110010 0
b10011011 ;
b100 *
b100 /
b10011010 -
1'
#1650000
0'
#1655000
b1110010 0
b10011100 ;
b10001 *
b10001 /
b10011011 -
1'
#1660000
0'
#1665000
b101110010 0
b10011101 ;
b11101 *
b11101 /
b10011100 -
1'
#1670000
0'
#1675000
b11110010 0
b10011110 ;
b101000 *
b101000 /
b10011101 -
1'
#1680000
0'
#1685000
b111110010 0
b10011111 ;
b110011 *
b110011 /
b10011110 -
1'
#1690000
0'
#1695000
b1010 0
b10100000 ;
b111101 *
b111101 /
b10011111 -
1'
#1700000
0'
#1705000
b100001010 0
b10100001 ;
b1000110 *
b1000110 /
b10100000 -
1'
#1710000
0'
#1715000
b10001010 0
b10100010 ;
b1001110 *
b1001110 /
b10100001 -
1'
#1720000
0'
#1725000
b110001010 0
b10100011 ;
b1010101 *
b1010101 /
b10100010 -
1'
#1730000
0'
#1735000
b1001010 0
b10100100 ;
b1011011 *
b1011011 /
b10100011 -
1'
#1740000
0'
#1745000
b101001010 0
b10100101 ;
b1011111 *
b1011111 /
b10100100 -
1'
#1750000
0'
#1755000
b11001010 0
b10100110 ;
b1100010 *
b1100010 /
b10100101 -
1'
#1760000
0'
#1765000
b111001010 0
b10100111 ;
b1100011 *
b1100011 /
b10100110 -
1'
#1770000
0'
#1775000
b101010 0
b10101000 ;
b10100111 -
1'
#1780000
0'
#1785000
b100101010 0
b10101001 ;
b1100010 *
b1100010 /
b10101000 -
1'
#1790000
0'
#1795000
b10101010 0
b10101010 ;
b1011110 *
b1011110 /
b10101001 -
1'
#1800000
0'
#1805000
b110101010 0
b10101011 ;
b1011010 *
b1011010 /
b10101010 -
1'
#1810000
0'
#1815000
b1101010 0
b10101100 ;
b1010100 *
b1010100 /
b10101011 -
1'
#1820000
0'
#1825000
b101101010 0
b10101101 ;
b1001101 *
b1001101 /
b10101100 -
1'
#1830000
0'
#1835000
b11101010 0
b10101110 ;
b1000100 *
b1000100 /
b10101101 -
1'
#1840000
0'
#1845000
b111101010 0
b10101111 ;
b111011 *
b111011 /
b10101110 -
1'
#1850000
0'
#1855000
b11010 0
b10110000 ;
b110001 *
b110001 /
b10101111 -
1'
#1860000
0'
#1865000
b100011010 0
b10110001 ;
b100110 *
b100110 /
b10110000 -
1'
#1870000
0'
#1875000
b10011010 0
b10110010 ;
b11010 *
b11010 /
b10110001 -
1'
#1880000
0'
#1885000
b110011010 0
b10110011 ;
b1110 *
b1110 /
b10110010 -
1'
#1890000
0'
#1895000
b1011010 0
b10110100 ;
b10 *
b10 /
b10110011 -
1'
#1900000
0'
#1905000
b101011010 0
b10110101 ;
b111111111111111111110111 *
b111111111111111111110111 /
b10110100 -
1'
#1910000
0'
#1915000
b11011010 0
b10110110 ;
b111111111111111111101011 *
b111111111111111111101011 /
b10110101 -
1'
#1920000
0'
#1925000
b111011010 0
b10110111 ;
b111111111111111111011111 *
b111111111111111111011111 /
b10110110 -
1'
#1930000
0'
#1935000
b111010 0
b10111000 ;
b111111111111111111010100 *
b111111111111111111010100 /
b10110111 -
1'
#1940000
0'
#1945000
b100111010 0
b10111001 ;
b111111111111111111001001 *
b111111111111111111001001 /
b10111000 -
1'
#1950000
0'
#1955000
b10111010 0
b10111010 ;
b111111111111111110111111 *
b111111111111111110111111 /
b10111001 -
1'
#1960000
0'
#1965000
b110111010 0
b10111011 ;
b111111111111111110110110 *
b111111111111111110110110 /
b10111010 -
1'
#1970000
0'
#1975000
b1111010 0
b10111100 ;
b111111111111111110101111 *
b111111111111111110101111 /
b10111011 -
1'
#1980000
0'
#1985000
b101111010 0
b10111101 ;
b111111111111111110101000 *
b111111111111111110101000 /
b10111100 -
1'
#1990000
0'
#1995000
b11111010 0
b10111110 ;
b111111111111111110100011 *
b111111111111111110100011 /
b10111101 -
1'
#2000000
0'
#2005000
b111111010 0
b10111111 ;
b111111111111111110011111 *
b111111111111111110011111 /
b10111110 -
1'
#2010000
0'
#2015000
b110 0
b11000000 ;
b111111111111111110011101 *
b111111111111111110011101 /
b10111111 -
1'
#2020000
0'
#2025000
b100000110 0
b11000001 ;
b111111111111111110011100 *
b111111111111111110011100 /
b11000000 -
1'
#2030000
0'
#2035000
b10000110 0
b11000010 ;
b111111111111111110011101 *
b111111111111111110011101 /
b11000001 -
1'
#2040000
0'
#2045000
b110000110 0
b11000011 ;
b111111111111111110011111 *
b111111111111111110011111 /
b11000010 -
1'
#2050000
0'
#2055000
b1000110 0
b11000100 ;
b111111111111111110100011 *
b111111111111111110100011 /
b11000011 -
1'
#2060000
0'
#2065000
b101000110 0
b11000101 ;
b111111111111111110101000 *
b111111111111111110101000 /
b11000100 -
1'
#2070000
0'
#2075000
b11000110 0
b11000110 ;
b111111111111111110101111 *
b111111111111111110101111 /
b11000101 -
1'
#2080000
0'
#2085000
b111000110 0
b11000111 ;
b111111111111111110110110 *
b111111111111111110110110 /
b11000110 -
1'
#2090000
0'
#2095000
b100110 0
b11001000 ;
b111111111111111110111111 *
b111111111111111110111111 /
b11000111 -
1'
#2100000
0'
#2105000
b100100110 0
b11001001 ;
b111111111111111111001001 *
b111111111111111111001001 /
b11001000 -
1'
#2110000
0'
