FILTERS/bandpass/second_order_bpf.sv
module second_order_bpf #(
    parameter int WIDTH = 16,

    // coefficients scaled by 2^14
    parameter logic signed [15:0] B0 = 16'sd16384,
    parameter logic signed [15:0] B1 = 16'sd0,
    parameter logic signed [15:0] B2 = -16'sd16384,
    parameter logic signed [15:0] A1 = 16'sd0,
    parameter logic signed [15:0] A2 = 16'sd0
)(
    input  logic clk,
    input  logic reset,
    input  logic signed [WIDTH-1:0] x,
    output logic signed [WIDTH-1:0] y
);

    logic signed [WIDTH-1:0] x1, x2;
    logic signed [WIDTH-1:0] y1, y2;

    logic signed [WIDTH + 16-1:0] prod_b0, prod_b1, prod_b2;
    logic signed [WIDTH + 16-1:0] prod_a1, prod_a2;
    logic signed [WIDTH + 19-1:0]  y_raw;
    logic signed [WIDTH-1:0]  y_next;

    // direct form I: y[n] = (b0 * x[0]) + (b1 * x[1]) + (b2 * x[2]) - (a1 * x[1])- (a2 * x[2])
    always_comb begin
        prod_b0 = x  * B0;
        prod_b1 = x1 * B1;
        prod_b2 = x2 * B2;
        prod_a1 = y1 * A1;
        prod_a2 = y2 * A2;

        y_raw = prod_b0 + prod_b1 + prod_b2 - prod_a1 - prod_a2;
        y_next = y_raw >>> 14;
    end

    always_ff @(posedge clk or posedge reset) begin
        if (reset) begin
            x1 <= '0;
            x2 <= '0;
            y1 <= '0;
            y2 <= '0;
            y  <= '0;
        end else begin
            y <= y_next;
            x2 <= x1;
            x1 <= x;
            y2 <= y1;
            y1 <= y_next;
        end
    end

endmodule

FILTERS/bandpass/fourth_order_bpf.sv
module fourth_order_bpf #(
    parameter SAMPLE_WIDTH = 16
)(
    input logic clk,
    input logic reset,
    input logic signed [SAMPLE_WIDTH - 1:0] data_in,
    output logic signed [SAMPLE_WIDTH - 1:0] data_out
);

  logic signed [SAMPLE_WIDTH-1:0] intermediate;

  // Section 1
  second_order_bpf stage1 (
      .clk(clk),
      .reset(reset),
      .x(data_in),
      .y(intermediate)
  );

  // Section 2
  second_order_bpf stage2 (
      .clk(clk),
      .reset(reset),
      .x(intermediate),
      .y(data_out)
  );
endmodule

FILTERS/bandpass/testbench.sv
`timescale 1ns/1ps

module tb_fourth_order_bpf;

    logic clk;
    logic reset;

    logic signed [15:0] data_in;
    logic signed [15:0] data_out;

    real fs = 48000.0;

    integer i;
    integer fout;

    real t;
    real value;

    fourth_order_bpf dut (
        .clk(clk),
        .reset(reset),
        .data_in(data_in),
        .data_out(data_out)
    );

    // clock
    initial clk = 0;
    always #5 clk = ~clk;

    initial begin
        $dumpfile("bpf.vcd");
        $dumpvars(0, tb_fourth_order_bpf);
    end

    initial begin

        fout = $fopen("bpf_samples.txt","w");

        reset = 1;
        data_in = 0;

        repeat(4) @(posedge clk);
        reset = 0;

        // -----------------------------
        // 100 Hz (below passband)
        // -----------------------------
        for(i = 0; i < 512; i++) begin
            @(posedge clk);

            t = i/fs;
            value = $cos(2.0 * 3.1415926535 * 100.0 * t);

            data_in = $rtoi(value * 12000);

            $fwrite(fout,"100Hz in=%0d out=%0d\n", data_in, data_out);
        end

        // -----------------------------
        // 1000 Hz (inside passband)
        // -----------------------------
        for(i = 0; i < 512; i++) begin
            @(posedge clk);

            t = i/fs;
            value = $cos(2.0 * 3.1415926535 * 1000.0 * t);

            data_in = $rtoi(value * 12000);

            $fwrite(fout,"1000Hz in=%0d out=%0d\n", data_in, data_out);
        end

        // -----------------------------
        // 8000 Hz (above passband)
        // -----------------------------
        for(i = 0; i < 512; i++) begin
            @(posedge clk);

            t = i/fs;
            value = $cos(2.0 * 3.1415926535 * 8000.0 * t);

            data_in = $rtoi(value * 12000);

            $fwrite(fout,"8000Hz in=%0d out=%0d\n", data_in, data_out);
        end

        $fclose(fout);

        repeat(10) @(posedge clk);
        $finish;

    end

endmodule

FILTERS/bandpass/bpf.vcd
$date
	Fri Mar 13 11:24:53 2026
$end
$version
	Icarus Verilog
$end
$timescale
	1ps
$end
$scope module tb_fourth_order_bpf $end
$var wire 16 ! data_out [15:0] $end
$var reg 1 " clk $end
$var reg 16 # data_in [15:0] $end
$var reg 1 $ reset $end
$var integer 32 % fout [31:0] $end
$var real 1 & fs $end
$var integer 32 ' i [31:0] $end
$var real 1 ( t $end
$var real 1 ) value $end
$scope module dut $end
$var wire 1 " clk $end
$var wire 16 * data_in [15:0] $end
$var wire 1 $ reset $end
$var wire 16 + intermediate [15:0] $end
$var wire 16 , data_out [15:0] $end
$var parameter 32 - SAMPLE_WIDTH $end
$scope module stage1 $end
$var wire 1 " clk $end
$var wire 1 $ reset $end
$var wire 16 . x [15:0] $end
$var parameter 16 / A1 $end
$var parameter 16 0 A2 $end
$var parameter 16 1 B0 $end
$var parameter 16 2 B1 $end
$var parameter 16 3 B2 $end
$var parameter 32 4 WIDTH $end
$var reg 32 5 prod_a1 [31:0] $end
$var reg 32 6 prod_a2 [31:0] $end
$var reg 32 7 prod_b0 [31:0] $end
$var reg 32 8 prod_b1 [31:0] $end
$var reg 32 9 prod_b2 [31:0] $end
$var reg 16 : x1 [15:0] $end
$var reg 16 ; x2 [15:0] $end
$var reg 16 < y [15:0] $end
$var reg 16 = y1 [15:0] $end
$var reg 16 > y2 [15:0] $end
$var reg 16 ? y_next [15:0] $end
$var reg 35 @ y_raw [34:0] $end
$upscope $end
$scope module stage2 $end
$var wire 1 " clk $end
$var wire 1 $ reset $end
$var wire 16 A x [15:0] $end
$var parameter 16 B A1 $end
$var parameter 16 C A2 $end
$var parameter 16 D B0 $end
$var parameter 16 E B1 $end
$var parameter 16 F B2 $end
$var parameter 32 G WIDTH $end
$var reg 32 H prod_a1 [31:0] $end
$var reg 32 I prod_a2 [31:0] $end
$var reg 32 J prod_b0 [31:0] $end
$var reg 32 K prod_b1 [31:0] $end
$var reg 32 L prod_b2 [31:0] $end
$var reg 16 M x1 [15:0] $end
$var reg 16 N x2 [15:0] $end
$var reg 16 O y [15:0] $end
$var reg 16 P y1 [15:0] $end
$var reg 16 Q y2 [15:0] $end
$var reg 16 R y_next [15:0] $end
$var reg 35 S y_raw [34:0] $end
$upscope $end
$upscope $end
$upscope $end
$enddefinitions $end
$comment Show the parameter values. $end
$dumpall
b10000 G
b1100000000000000 F
b0 E
b100000000000000 D
b0 C
b0 B
b10000 4
b1100000000000000 3
b0 2
b100000000000000 1
b0 0
b0 /
b10000 -
$end
#0
$dumpvars
b0 S
b0 R
b0 Q
b0 P
b0 O
b0 N
b0 M
b0 L
b0 K
b0 J
b0 I
b0 H
b0 A
b0 @
b0 ?
b0 >
b0 =
b0 <
b0 ;
b0 :
b0 9
b0 8
b0 7
b0 6
b0 5
b0 .
b0 ,
b0 +
b0 *
r0 )
r0 (
bx '
r48000 &
b10000000000000000000000000000011 %
1$
b0 #
0"
b0 !
$end
#5000
1"
#10000
0"
#15000
1"
#20000
0"
#25000
1"
#30000
0"
#35000
b0 '
0$
1"
#40000
0"
#45000
b10111011100000 :
b10111011100000 ?
b1011101110000000000000000000 @
b1011101110000000000000000000 7
b1 '
b10111011100000 #
b10111011100000 *
b10111011100000 .
r1 )
1"
#50000
0"
#55000
b11110100010010000000000000000000 9
b10111011100000 R
b1011101110000000000000000000 S
b1011101110000000000000000000 J
b10111011100000 =
b10111011011110 :
b10111011100000 ;
b10111011100000 +
b10111011100000 <
b10111011100000 A
b1111111111111110 ?
b11111111111111111111000000000000000 @
b1011101101111000000000000000 7
b10 '
b10111011011110 #
b10111011011110 *
b10111011011110 .
r0.9999143275740119 )
r2.083333333333333e-05 (
1"
#60000
0"
#65000
b11110100010010001000000000000000 9
b1111111111111110 R
b11111111111111111111000000000000000 S
b11111111111111111000000000000000 J
b10111011100000 P
b10111011100000 M
b10111011100000 !
b10111011100000 ,
b10111011100000 O
b1111111111111110 =
b10111011100000 >
b10111011011011 :
b10111011011110 ;
b1111111111111110 +
b1111111111111110 <
b1111111111111110 A
b1111111111111101 ?
b11111111111111111110100000000000000 @
b1011101101101100000000000000 7
b11 '
b10111011011011 #
b10111011011011 *
b10111011011011 .
r0.9996573249755769 )
r4.166666666666667e-05 (
1"
#70000
0"
#75000
b11110100010010010100000000000000 9
b1101000100011101 R
b11111110100010001110100000000000000 S
b11110100010010000000000000000000 L
b11111111111111110100000000000000 J
b1111111111111101 =
b1111111111111110 >
b10111011010110 :
b10111011011011 ;
b1111111111111101 +
b1111111111111101 <
b1111111111111101 A
b1111111111111110 P
b10111011100000 Q
b1111111111111110 M
b10111011100000 N
b1111111111111110 !
b1111111111111110 ,
b1111111111111110 O
b1111111111111011 ?
b11111111111111111101100000000000000 @
b1011101101011000000000000000 7
b100 '
b10111011010110 #
b10111011010110 *
b10111011010110 .
r0.999229036240767 )
r6.25e-05 (
1"
#80000
0"
#85000
b11110100010010101000000000000000 9
b1111111111111101 R
b11111111111111111110100000000000000 S
b1000000000000000 L
b11111111111111101100000000000000 J
b1101000100011101 P
b1111111111111110 Q
b1111111111111101 M
b1111111111111110 N
b1101000100011101 !
b1101000100011101 ,
b1101000100011101 O
b1111111111111011 =
b1111111111111101 >
b10111011001111 :
b10111011010110 ;
b1111111111111011 +
b1111111111111011 <
b1111111111111011 A
b1111111111111001 ?
b11111111111111111100100000000000000 @
b1011101100111100000000000000 7
b101 '
b10111011001111 #
b10111011001111 *
b10111011001111 .
r0.9986295347546522 )
r8.333333333333333e-05 (
1"
#90000
0"
#95000
b11110100010011000100000000000000 9
b1111111111111100 R
b11111111111111111110000000000000000 S
b1100000000000000 L
b11111111111111100100000000000000 J
b1111111111111001 =
b1111111111111011 >
b10111011000110 :
b10111011001111 ;
b1111111111111001 +
b1111111111111001 <
b1111111111111001 A
b1111111111111101 P
b1101000100011101 Q
b1111111111111011 M
b1111111111111101 N
b1111111111111101 !
b1111111111111101 ,
b1111111111111101 O
b1111111111110111 ?
b11111111111111111011100000000000000 @
b1011101100011000000000000000 7
b110 '
b10111011000110 #
b10111011000110 *
b10111011000110 .
r0.9978589232387258 )
r0.0001041666666666667 (
1"
#100000
0"
#105000
b11110100010011101000000000000000 9
b10100000000000000 L
b11111111111111011100000000000000 J
b1111111111111100 P
b1111111111111101 Q
b1111111111111001 M
b1111111111111011 N
b1111111111111100 !
b1111111111111100 ,
b1111111111111100 O
b1111111111110111 =
b1111111111111001 >
b10111010111011 :
b10111011000110 ;
b1111111111110111 +
b1111111111110111 <
b1111111111110111 A
b1111111111110101 ?
b11111111111111111010100000000000000 @
b1011101011101100000000000000 7
b111 '
b10111010111011 #
b10111010111011 *
b10111010111011 .
r0.9969173337333042 )
r0.000125 (
1"
#110000
0"
#115000
b11110100010100010100000000000000 9
b11100000000000000 L
b11111111111111010100000000000000 J
b1111111111110101 =
b1111111111110111 >
b10111010101101 :
b10111010111011 ;
b1111111111110101 +
b1111111111110101 <
b1111111111110101 A
b1111111111111100 Q
b1111111111110111 M
b1111111111111001 N
b1111111111110010 ?
b11111111111111111001000000000000000 @
b1011101010110100000000000000 7
b1000 '
b10111010101101 #
b10111010101101 *
b10111010101101 .
r0.9958049275749014 )
r0.0001458333333333333 (
1"
#120000
0"
#125000
b11110100010101001100000000000000 9
b1111111111111011 R
b11111111111111111101100000000000000 S
b100100000000000000 L
b11111111111111001000000000000000 J
b1111111111110101 M
b1111111111110111 N
b1111111111110010 =
b1111111111110101 >
b10111010011110 :
b10111010101101 ;
b1111111111110010 +
b1111111111110010 <
b1111111111110010 A
b1111111111110001 ?
b11111111111111111000100000000000000 @
b1011101001111000000000000000 7
b1001 '
b10111010011110 #
b10111010011110 *
b10111010011110 .
r0.9945218953685862 )
r0.0001666666666666667 (
1"
#130000
0"
#135000
b11110100010110001000000000000000 9
b1111111111111100 R
b11111111111111111110000000000000000 S
b101100000000000000 L
b11111111111111000100000000000000 J
b1111111111110001 =
b1111111111110010 >
b10111010001100 :
b10111010011110 ;
b1111111111110001 +
b1111111111110001 <
b1111111111110001 A
b1111111111111011 P
b1111111111110010 M
b1111111111110101 N
b1111111111111011 !
b1111111111111011 ,
b1111111111111011 O
b1111111111101110 ?
b11111111111111110111000000000000000 @
b1011101000110000000000000000 7
b1010 '
b10111010001100 #
b10111010001100 *
b10111010001100 .
r0.9930684569553221 )
r0.0001875 (
1"
#140000
0"
#145000
b11110100010111010000000000000000 9
b111000000000000000 L
b11111111111110111000000000000000 J
b1111111111111100 P
b1111111111111011 Q
b1111111111110001 M
b1111111111110010 N
b1111111111111100 !
b1111111111111100 ,
b1111111111111100 O
b1111111111101110 =
b1111111111110001 >
b10111001111001 :
b10111010001100 ;
b1111111111101110 +
b1111111111101110 <
b1111111111101110 A
b1111111111101101 ?
b11111111111111110110100000000000000 @
b1011100111100100000000000000 7
b1011 '
b10111001111001 #
b10111001111001 *
b10111001111001 .
r0.9914448613742988 )
r0.0002083333333333333 (
1"
#150000
0"
#155000
b11110100011000011100000000000000 9
b111100000000000000 L
b11111111111110110100000000000000 J
b1111111111101101 =
b1111111111101110 >
b10111001100011 :
b10111001111001 ;
b1111111111101101 +
b1111111111101101 <
b1111111111101101 A
b1111111111111100 Q
b1111111111101110 M
b1111111111110001 N
b1111111111101010 ?
b11111111111111110101000000000000000 @
b1011100110001100000000000000 7
b1100 '
b10111001100011 #
b10111001100011 *
b10111001100011 .
r0.9896513868202608 )
r0.0002291666666666667 (
1"
#160000
0"
#165000
b11110100011001110100000000000000 9
b1001000000000000000 L
b11111111111110101000000000000000 J
b1111111111101101 M
b1111111111101110 N
b1111111111101010 =
b1111111111101101 >
b10111001001100 :
b10111001100011 ;
b1111111111101010 +
b1111111111101010 <
b1111111111101010 A
b1111111111101001 ?
b11111111111111110100100000000000000 @
b1011100100110000000000000000 7
b1101 '
b10111001001100 #
b10111001001100 *
b10111001001100 .
r0.9876883405958401 )
r0.00025 (
1"
#170000
0"
#175000
b11110100011011010000000000000000 9
b1001100000000000000 L
b11111111111110100100000000000000 J
b1111111111101001 =
b1111111111101010 >
b10111000110010 :
b10111001001100 ;
b1111111111101001 +
b1111111111101001 <
b1111111111101001 A
b1111111111101010 M
b1111111111101101 N
b1111111111100110 ?
b11111111111111110011000000000000000 @
b1011100011001000000000000000 7
b1110 '
b10111000110010 #
b10111000110010 *
b10111000110010 .
r0.9855560590589014 )
r0.0002708333333333333 (
1"
#180000
0"
#185000
b11110100011100111000000000000000 9
b1011000000000000000 L
b11111111111110011000000000000000 J
b1111111111101001 M
b1111111111101010 N
b1111111111100110 =
b1111111111101001 >
b10111000010111 :
b10111000110010 ;
b1111111111100110 +
b1111111111100110 <
b1111111111100110 A
b1111111111100101 ?
b11111111111111110010100000000000000 @
b1011100001011100000000000000 7
b1111 '
b10111000010111 #
b10111000010111 *
b10111000010111 .
r0.9832549075649091 )
r0.0002916666666666667 (
1"
#190000
0"
#195000
b11110100011110100100000000000000 9
b1011100000000000000 L
b11111111111110010100000000000000 J
b1111111111100101 =
b1111111111100110 >
b10110111111001 :
b10111000010111 ;
b1111111111100101 +
b1111111111100101 <
b1111111111100101 A
b1111111111100110 M
b1111111111101001 N
b1111111111100010 ?
b11111111111111110001000000000000000 @
b1011011111100100000000000000 7
b10000 '
b10110111111001 #
b10110111111001 *
b10110111111001 .
r0.9807852804043253 )
r0.0003125 (
1"
#200000
0"
#205000
b11110100100000011100000000000000 9
b1101000000000000000 L
b11111111111110001000000000000000 J
b1111111111100101 M
b1111111111100110 N
b1111111111100010 =
b1111111111100101 >
b10110111011001 :
b10110111111001 ;
b1111111111100010 +
b1111111111100010 <
b1111111111100010 A
b1111111111100000 ?
b11111111111111110000000000000000000 @
b1011011101100100000000000000 7
b10001 '
b10110111011001 #
b10110111011001 *
b10110111011001 .
r0.9781476007350502 )
r0.0003333333333333333 (
1"
#210000
0"
#215000
b11110100100010011100000000000000 9
b1111111111111011 R
b11111111111111111101100000000000000 S
b1101100000000000000 L
b11111111111110000000000000000000 J
b1111111111100000 =
b1111111111100010 >
b10110110111000 :
b10110111011001 ;
b1111111111100000 +
b1111111111100000 <
b1111111111100000 A
b1111111111100010 M
b1111111111100101 N
b1111111111011111 ?
b11111111111111101111100000000000000 @
b1011011011100000000000000000 7
b10010 '
b10110110111000 #
b10110110111000 *
b10110110111000 .
r0.9753423205099164 )
r0.0003541666666666667 (
1"
#220000
0"
#225000
b11110100100100100000000000000000 9
b1111111111111101 R
b11111111111111111110100000000000000 S
b1111000000000000000 L
b11111111111101111100000000000000 J
b1111111111111011 P
b1111111111100000 M
b1111111111100010 N
b1111111111111011 !
b1111111111111011 ,
b1111111111111011 O
b1111111111011111 =
b1111111111100000 >
b10110110010100 :
b10110110111000 ;
b1111111111011111 +
b1111111111011111 <
b1111111111011111 A
b1111111111011100 ?
b11111111111111101110000000000000000 @
b1011011001010000000000000000 7
b10011 '
b10110110010100 #
b10110110010100 *
b10110110010100 .
r0.9723699203992487 )
r0.000375 (
1"
#230000
0"
#235000
b11110100100110110000000000000000 9
b1111111111111100 R
b11111111111111111110000000000000000 S
b10000000000000000000 L
b11111111111101110000000000000000 J
b1111111111011100 =
b1111111111011111 >
b10110101101110 :
b10110110010100 ;
b1111111111011100 +
b1111111111011100 <
b1111111111011100 A
b1111111111111101 P
b1111111111111011 Q
b1111111111011111 M
b1111111111100000 N
b1111111111111101 !
b1111111111111101 ,
b1111111111111101 O
b1111111111011010 ?
b11111111111111101101000000000000000 @
b1011010110111000000000000000 7
b10100 '
b10110101101110 #
b10110101101110 *
b10110101101110 .
r0.9692309097085042 )
r0.0003958333333333333 (
1"
#240000
0"
#245000
b11110100101001001000000000000000 9
b1111111111111011 R
b11111111111111111101100000000000000 S
b10000100000000000000 L
b11111111111101101000000000000000 J
b1111111111111100 P
b1111111111111101 Q
b1111111111011100 M
b1111111111011111 N
b1111111111111100 !
b1111111111111100 ,
b1111111111111100 O
b1111111111011010 =
b1111111111011100 >
b10110101000111 :
b10110101101110 ;
b1111111111011010 +
b1111111111011010 <
b1111111111011010 A
b1111111111011001 ?
b11111111111111101100100000000000000 @
b1011010100011100000000000000 7
b10101 '
b10110101000111 #
b10110101000111 *
b10110101000111 .
r0.965925826291005 )
r0.0004166666666666667 (
1"
#250000
0"
#255000
b11110100101011100100000000000000 9
b1111111111111101 R
b11111111111111111110100000000000000 S
b10010000000000000000 L
b11111111111101100100000000000000 J
b1111111111011001 =
b1111111111011010 >
b10110100011101 :
b10110101000111 ;
b1111111111011001 +
b1111111111011001 <
b1111111111011001 A
b1111111111111011 P
b1111111111111100 Q
b1111111111011010 M
b1111111111011100 N
b1111111111111011 !
b1111111111111011 ,
b1111111111111011 O
b1111111111010110 ?
b11111111111111101011000000000000000 @
b1011010001110100000000000000 7
b10110 '
b10110100011101 #
b10110100011101 *
b10110100011101 .
r0.96245523645578 )
r0.0004375 (
1"
#260000
0"
#265000
b11110100101110001100000000000000 9
b1111111111111100 R
b11111111111111111110000000000000000 S
b10011000000000000000 L
b11111111111101011000000000000000 J
b1111111111111101 P
b1111111111111011 Q
b1111111111011001 M
b1111111111011010 N
b1111111111111101 !
b1111111111111101 ,
b1111111111111101 O
b1111111111010110 =
b1111111111011001 >
b10110011110001 :
b10110100011101 ;
b1111111111010110 +
b1111111111010110 <
b1111111111010110 A
b1111111111010100 ?
b11111111111111101010000000000000000 @
b1011001111000100000000000000 7
b10111 '
b10110011110001 #
b10110011110001 *
b10110011110001 .
r0.9588197348705308 )
r0.0004583333333333333 (
1"
#270000
0"
#275000
b11110100110000111100000000000000 9
b1111111111111011 R
b11111111111111111101100000000000000 S
b10011100000000000000 L
b11111111111101010000000000000000 J
b1111111111010100 =
b1111111111010110 >
b10110011000100 :
b10110011110001 ;
b1111111111010100 +
b1111111111010100 <
b1111111111010100 A
b1111111111111100 P
b1111111111111101 Q
b1111111111010110 M
b1111111111011001 N
b1111111111111100 !
b1111111111111100 ,
b1111111111111100 O
b1111111111010011 ?
b11111111111111101001100000000000000 @
b1011001100010000000000000000 7
b11000 '
b10110011000100 #
b10110011000100 *
b10110011000100 .
r0.9550199444597385 )
r0.0004791666666666666 (
1"
#280000
0"
#285000
b11110100110011110000000000000000 9
b1111111111111101 R
b11111111111111111110100000000000000 S
b10101000000000000000 L
b11111111111101001100000000000000 J
b1111111111111011 P
b1111111111111100 Q
b1111111111010100 M
b1111111111010110 N
b1111111111111011 !
b1111111111111011 ,
b1111111111111011 O
b1111111111010011 =
b1111111111010100 >
b10110010010100 :
b10110011000100 ;
b1111111111010011 +
b1111111111010011 <
b1111111111010011 A
b1111111111010000 ?
b11111111111111101000000000000000000 @
b1011001001010000000000000000 7
b11001 '
b10110010010100 #
b10110010010100 *
b10110010010100 .
r0.9510565162979283 )
r0.0005 (
1"
#290000
0"
#295000
b11110100110110110000000000000000 9
b1111111111111100 R
b11111111111111111110000000000000000 S
b10110000000000000000 L
b11111111111101000000000000000000 J
b1111111111010000 =
b1111111111010011 >
b10110001100011 :
b10110010010100 ;
b1111111111010000 +
b1111111111010000 <
b1111111111010000 A
b1111111111111101 P
b1111111111111011 Q
b1111111111010011 M
b1111111111010100 N
b1111111111111101 !
b1111111111111101 ,
b1111111111111101 O
b1111111111001111 ?
b11111111111111100111100000000000000 @
b1011000110001100000000000000 7
b11010 '
b10110001100011 #
b10110001100011 *
b10110001100011 .
r0.9469301294981123 )
r0.0005208333333333333 (
1"
#300000
0"
#305000
b11110100111001110100000000000000 9
b10110100000000000000 L
b11111111111100111100000000000000 J
b1111111111111100 P
b1111111111111101 Q
b1111111111010000 M
b1111111111010011 N
b1111111111111100 !
b1111111111111100 ,
b1111111111111100 O
b1111111111001111 =
b1111111111010000 >
b10110000101111 :
b10110001100011 ;
b1111111111001111 +
b1111111111001111 <
b1111111111001111 A
b1111111111001100 ?
b11111111111111100110000000000000000 @
b1011000010111100000000000000 7
b11011 '
b10110000101111 #
b10110000101111 *
b10110000101111 .
r0.9426414910954255 )
r0.0005416666666666666 (
1"
#310000
0"
#315000
b11110100111101000100000000000000 9
b11000000000000000000 L
b11111111111100110000000000000000 J
b1111111111001100 =
b1111111111001111 >
b10101111111010 :
b10110000101111 ;
b1111111111001100 +
b1111111111001100 <
b1111111111001100 A
b1111111111111100 Q
b1111111111001111 M
b1111111111010000 N
b1111111111001011 ?
b11111111111111100101100000000000000 @
b1010111111101000000000000000 7
b11100 '
b10101111111010 #
b10101111111010 *
b10101111111010 .
r0.9381913359259805 )
r0.0005625 (
1"
#320000
0"
#325000
b11110101000000011000000000000000 9
b11000100000000000000 L
b11111111111100101100000000000000 J
b1111111111001100 M
b1111111111001111 N
b1111111111001011 =
b1111111111001100 >
b10101111000010 :
b10101111111010 ;
b1111111111001011 +
b1111111111001011 <
b1111111111001011 A
b1111111111001000 ?
b11111111111111100100000000000000000 @
b1010111100001000000000000000 7
b11101 '
b10101111000010 #
b10101111000010 *
b10101111000010 .
r0.933580426500956 )
r0.0005833333333333334 (
1"
#330000
0"
#335000
b11110101000011111000000000000000 9
b11010000000000000000 L
b11111111111100100000000000000000 J
b1111111111001000 =
b1111111111001011 >
b10101110001001 :
b10101111000010 ;
b1111111111001000 +
b1111111111001000 <
b1111111111001000 A
b1111111111001011 M
b1111111111001100 N
b1111111111000111 ?
b11111111111111100011100000000000000 @
b1010111000100100000000000000 7
b11110 '
b10101110001001 #
b10101110001001 *
b10101110001001 .
r0.9288095528759448 )
r0.0006041666666666667 (
1"
#340000
0"
#345000
b11110101000111011100000000000000 9
b11010100000000000000 L
b11111111111100011100000000000000 J
b1111111111001000 M
b1111111111001011 N
b1111111111000111 =
b1111111111001000 >
b10101101001110 :
b10101110001001 ;
b1111111111000111 +
b1111111111000111 <
b1111111111000111 A
b1111111111000101 ?
b11111111111111100010100000000000000 @
b1010110100111000000000000000 7
b11111 '
b10101101001110 #
b10101101001110 *
b10101101001110 .
r0.9238795325155821 )
r0.000625 (
1"
#350000
0"
#355000
b11110101001011001000000000000000 9
b1111111111111101 R
b11111111111111111110100000000000000 S
b11100000000000000000 L
b11111111111100010100000000000000 J
b1111111111000101 =
b1111111111000111 >
b10101100010001 :
b10101101001110 ;
b1111111111000101 +
b1111111111000101 <
b1111111111000101 A
b1111111111000111 M
b1111111111001000 N
b1111111111000011 ?
b11111111111111100001100000000000000 @
b1010110001000100000000000000 7
b100000 '
b10101100010001 #
b10101100010001 *
b10101100010001 .
r0.9187912101534766 )
r0.0006458333333333333 (
1"
#360000
0"
#365000
b11110101001110111100000000000000 9
b1111111111111100 R
b11111111111111111110000000000000000 S
b11100100000000000000 L
b11111111111100001100000000000000 J
b1111111111111101 P
b1111111111000101 M
b1111111111000111 N
b1111111111111101 !
b1111111111111101 ,
b1111111111111101 O
b1111111111000011 =
b1111111111000101 >
b10101011010010 :
b10101100010001 ;
b1111111111000011 +
b1111111111000011 <
b1111111111000011 A
b1111111111000001 ?
b11111111111111100000100000000000000 @
b1010101101001000000000000000 7
b100001 '
b10101011010010 #
b10101011010010 *
b10101011010010 .
r0.9135454576474705 )
r0.0006666666666666666 (
1"
#370000
0"
#375000
b11110101010010111000000000000000 9
b11101100000000000000 L
b11111111111100000100000000000000 J
b1111111111000001 =
b1111111111000011 >
b10101010010001 :
b10101011010010 ;
b1111111111000001 +
b1111111111000001 <
b1111111111000001 A
b1111111111111100 P
b1111111111111101 Q
b1111111111000011 M
b1111111111000101 N
b1111111111111100 !
b1111111111111100 ,
b1111111111111100 O
b1111111110111111 ?
b11111111111111011111100000000000000 @
b1010101001000100000000000000 7
b100010 '
b10101010010001 #
b10101010010001 *
b10101010010001 .
r0.9081431738302503 )
r0.0006875 (
1"
#380000
0"
#385000
b11110101010110111100000000000000 9
b11110100000000000000 L
b11111111111011111100000000000000 J
b1111111111111100 Q
b1111111111000001 M
b1111111111000011 N
b1111111110111111 =
b1111111111000001 >
b10101001001111 :
b10101010010001 ;
b1111111110111111 +
b1111111110111111 <
b1111111110111111 A
b1111111110111110 ?
b11111111111111011111000000000000000 @
b1010100100111100000000000000 7
b100011 '
b10101001001111 #
b10101001001111 *
b10101001001111 .
r0.902585284355337 )
r0.0007083333333333334 (
1"
#390000
0"
#395000
b11110101011011000100000000000000 9
b1111111111111101 R
b11111111111111111110100000000000000 S
b11111100000000000000 L
b11111111111011111000000000000000 J
b1111111110111110 =
b1111111110111111 >
b10101000001010 :
b10101001001111 ;
b1111111110111110 +
b1111111110111110 <
b1111111110111110 A
b1111111110111111 M
b1111111111000001 N
b1111111110111011 ?
b11111111111111011101100000000000000 @
b1010100000101000000000000000 7
b100100 '
b10101000001010 #
b10101000001010 *
b10101000001010 .
r0.89687274153848 )
r0.0007291666666666667 (
1"
#400000
0"
#405000
b11110101011111011000000000000000 9
b1111111111111100 R
b11111111111111111110000000000000000 S
b100000100000000000000 L
b11111111111011101100000000000000 J
b1111111111111101 P
b1111111110111110 M
b1111111110111111 N
b1111111111111101 !
b1111111111111101 ,
b1111111111111101 O
b1111111110111011 =
b1111111110111110 >
b10100111000100 :
b10101000001010 ;
b1111111110111011 +
b1111111110111011 <
b1111111110111011 A
b1111111110111010 ?
b11111111111111011101000000000000000 @
b1010011100010000000000000000 7
b100101 '
b10100111000100 #
b10100111000100 *
b10100111000100 .
r0.8910065241944827 )
r0.00075 (
1"
#410000
0"
#415000
b11110101100011110000000000000000 9
b100001000000000000000 L
b11111111111011101000000000000000 J
b1111111110111010 =
b1111111110111011 >
b10100101111011 :
b10100111000100 ;
b1111111110111010 +
b1111111110111010 <
b1111111110111010 A
b1111111111111100 P
b1111111111111101 Q
b1111111110111011 M
b1111111110111110 N
b1111111111111100 !
b1111111111111100 ,
b1111111111111100 O
b1111111110110111 ?
b11111111111111011011100000000000000 @
b1010010111101100000000000000 7
b100110 '
b10100101111011 #
b10100101111011 *
b10100101111011 .
r0.8849876374694874 )
r0.0007708333333333333 (
1"
#420000
0"
#425000
b11110101101000010100000000000000 9
b100010100000000000000 L
b11111111111011011100000000000000 J
b1111111111111100 Q
b1111111110111010 M
b1111111110111011 N
b1111111110110111 =
b1111111110111010 >
b10100100110001 :
b10100101111011 ;
b1111111110110111 +
b1111111110110111 <
b1111111110110111 A
b1111111110110110 ?
b11111111111111011011000000000000000 @
b1010010011000100000000000000 7
b100111 '
b10100100110001 #
b10100100110001 *
b10100100110001 .
r0.8788171126687493 )
r0.0007916666666666666 (
1"
#430000
0"
#435000
b11110101101100111100000000000000 9
b100011000000000000000 L
b11111111111011011000000000000000 J
b1111111110110110 =
b1111111110110111 >
b10100011100101 :
b10100100110001 ;
b1111111110110110 +
b1111111110110110 <
b1111111110110110 A
b1111111110110111 M
b1111111110111010 N
b1111111110110100 ?
b11111111111111011010000000000000000 @
b1010001110010100000000000000 7
b101000 '
b10100011100101 #
b10100011100101 *
b10100011100101 .
r0.8724960070799268 )
r0.0008125 (
1"
#440000
0"
#445000
b11110101110001101100000000000000 9
b1111111111111101 R
b11111111111111111110100000000000000 S
b100100100000000000000 L
b11111111111011010000000000000000 J
b1111111110110110 M
b1111111110110111 N
b1111111110110100 =
b1111111110110110 >
b10100010011000 :
b10100011100101 ;
b1111111110110100 +
b1111111110110100 <
b1111111110110100 A
b1111111110110011 ?
b11111111111111011001100000000000000 @
b1010001001100000000000000000 7
b101001 '
b10100010011000 #
b10100010011000 *
b10100010011000 .
r0.8660254037919214 )
r0.0008333333333333334 (
1"
#450000
0"
