FILTERS/bandpass/second_order_bpf.sv
module second_order_bpf #(
    parameter int WIDTH = 16,

    // coefficients scaled by 2^14
    parameter logic signed [15:0] B0 = 16'sd16384,
    parameter logic signed [15:0] B1 = 16'sd0,
    parameter logic signed [15:0] B2 = -16'sd16384,
    parameter logic signed [15:0] A1 = 16'sd0,
    parameter logic signed [15:0] A2 = 16'sd0
)(
    input  logic clk,
    input  logic reset,
    input  logic signed [WIDTH-1:0] x,
    output logic signed [WIDTH-1:0] y
);

    logic signed [WIDTH-1:0] x1, x2;
    logic signed [WIDTH-1:0] y1, y2;

    logic signed [WIDTH + 16-1:0] prod_b0, prod_b1, prod_b2;
    logic signed [WIDTH + 16-1:0] prod_a1, prod_a2;
    logic signed [WIDTH + 19-1:0]  y_raw;
    logic signed [WIDTH-1:0]  y_next;

    // direct form I: y[n] = (b0 * x[0]) + (b1 * x[1]) + (b2 * x[2]) - (a1 * x[1])- (a2 * x[2])
    always_comb begin
        prod_b0 = x  * B0;
        prod_b1 = x1 * B1;
        prod_b2 = x2 * B2;
        prod_a1 = y1 * A1;
        prod_a2 = y2 * A2;

        y_raw = prod_b0 + prod_b1 + prod_b2 - prod_a1 - prod_a2;
        y_next = y_raw >>> 14;
    end

    always_ff @(posedge clk or posedge reset) begin
        if (reset) begin
            x1 <= '0;
            x2 <= '0;
            y1 <= '0;
            y2 <= '0;
            y  <= '0;
        end else begin
            y <= y_next;
            x2 <= x1;
            x1 <= x;
            y2 <= y1;
            y1 <= y_next;
        end
    end

endmodule

FILTERS/bandpass/fourth_order_bpf.sv
module fourth_order_bpf #(
    parameter SAMPLE_WIDTH = 16
)(
    input logic clk,
    input logic reset,
    input logic signed [SAMPLE_WIDTH - 1:0] data_in,
    output logic signed [SAMPLE_WIDTH - 1:0] data_out
);

  logic signed [SAMPLE_WIDTH-1:0] intermediate;

  // Section 1
  second_order_bpf stage1 (
      .clk(clk),
      .reset(reset),
      .x(data_in),
      .y(intermediate)
  );

  // Section 2
  second_order_bpf stage2 (
      .clk(clk),
      .reset(reset),
      .x(intermediate),
      .y(data_out)
  );
endmodule

FILTERS/bandpass/testbench.sv
`timescale 1ns/1ps

module tb_fourth_order_bpf;

    logic clk;
    logic reset;

    logic signed [15:0] data_in;
    logic signed [15:0] data_out;

    real fs = 48000.0;

    integer i;
    integer fout;

    real t;
    real value;

    fourth_order_bpf dut (
        .clk(clk),
        .reset(reset),
        .data_in(data_in),
        .data_out(data_out)
    );

    // clock
    initial clk = 0;
    always #5 clk = ~clk;

    initial begin
        $dumpfile("bpf.vcd");
        $dumpvars(0, tb_fourth_order_bpf);
    end

    initial begin

        fout = $fopen("bpf_samples.txt","w");

        reset = 1;
        data_in = 0;

        repeat(4) @(posedge clk);
        reset = 0;

        // -----------------------------
        // 100 Hz (below passband)
        // -----------------------------
        for(i = 0; i < 512; i++) begin
            @(posedge clk);

            t = i/fs;
            value = $cos(2.0 * 3.1415926535 * 100.0 * t);

            data_in = $rtoi(value * 12000);

            $fwrite(fout,"100Hz in=%0d out=%0d\n", data_in, data_out);
        end

        // -----------------------------
        // 1000 Hz (inside passband)
        // -----------------------------
        for(i = 0; i < 512; i++) begin
            @(posedge clk);

            t = i/fs;
            value = $cos(2.0 * 3.1415926535 * 1000.0 * t);

            data_in = $rtoi(value * 12000);

            $fwrite(fout,"1000Hz in=%0d out=%0d\n", data_in, data_out);
        end

        // -----------------------------
        // 8000 Hz (above passband)
        // -----------------------------
        for(i = 0; i < 512; i++) begin
            @(posedge clk);

            t = i/fs;
            value = $cos(2.0 * 3.1415926535 * 8000.0 * t);

            data_in = $rtoi(value * 12000);

            $fwrite(fout,"8000Hz in=%0d out=%0d\n", data_in, data_out);
        end

        $fclose(fout);

        repeat(10) @(posedge clk);
        $finish;

    end

endmodule

FILTERS/bandpass/fourth_order_bpf.vcd
$date
	Fri Mar 13 10:14:42 2026
$end
$version
	Icarus Verilog
$end
$timescale
	1ps
$end
$scope module tb_fourth_order_bpf $end
$var wire 16 ! data_out [15:0] $end
$var reg 1 " clk $end
$var reg 16 # data_in [15:0] $end
$var reg 1 $ reset $end
$var integer 32 % fout [31:0] $end
$var integer 32 & i [31:0] $end
$scope function cos_lut $end
$upscope $end
$scope module dut $end
$var wire 1 " clk $end
$var wire 16 ' data_in [15:0] $end
$var wire 1 $ reset $end
$var wire 16 ( intermediate [15:0] $end
$var wire 16 ) data_out [15:0] $end
$var parameter 32 * SAMPLE_WIDTH $end
$scope module stage1 $end
$var wire 1 " clk $end
$var wire 1 $ reset $end
$var wire 16 + x [15:0] $end
$var parameter 16 , A1 $end
$var parameter 16 - A2 $end
$var parameter 16 . B0 $end
$var parameter 16 / B1 $end
$var parameter 16 0 B2 $end
$var parameter 32 1 WIDTH $end
$var reg 32 2 prod_a1 [31:0] $end
$var reg 32 3 prod_a2 [31:0] $end
$var reg 32 4 prod_b0 [31:0] $end
$var reg 32 5 prod_b1 [31:0] $end
$var reg 32 6 prod_b2 [31:0] $end
$var reg 16 7 x1 [15:0] $end
$var reg 16 8 x2 [15:0] $end
$var reg 16 9 y [15:0] $end
$var reg 16 : y1 [15:0] $end
$var reg 16 ; y2 [15:0] $end
$var reg 16 < y_next [15:0] $end
$var reg 35 = y_raw [34:0] $end
$upscope $end
$scope module stage2 $end
$var wire 1 " clk $end
$var wire 1 $ reset $end
$var wire 16 > x [15:0] $end
$var parameter 16 ? A1 $end
$var parameter 16 @ A2 $end
$var parameter 16 A B0 $end
$var parameter 16 B B1 $end
$var parameter 16 C B2 $end
$var parameter 32 D WIDTH $end
$var reg 32 E prod_a1 [31:0] $end
$var reg 32 F prod_a2 [31:0] $end
$var reg 32 G prod_b0 [31:0] $end
$var reg 32 H prod_b1 [31:0] $end
$var reg 32 I prod_b2 [31:0] $end
$var reg 16 J x1 [15:0] $end
$var reg 16 K x2 [15:0] $end
$var reg 16 L y [15:0] $end
$var reg 16 M y1 [15:0] $end
$var reg 16 N y2 [15:0] $end
$var reg 16 O y_next [15:0] $end
$var reg 35 P y_raw [34:0] $end
$upscope $end
$upscope $end
$upscope $end
$enddefinitions $end
$comment Show the parameter values. $end
$dumpall
b10000 D
b1100000000000000 C
b0 B
b100000000000000 A
b0 @
b0 ?
b10000 1
b1100000000000000 0
b0 /
b100000000000000 .
b0 -
b0 ,
b10000 *
$end
#0
$dumpvars
b0 P
b0 O
b0 N
b0 M
b0 L
b0 K
b0 J
b0 I
b0 H
b0 G
b0 F
b0 E
b0 >
b0 =
b0 <
b0 ;
b0 :
b0 9
b0 8
b0 7
b0 6
b0 5
b0 4
b0 3
b0 2
b0 +
b0 )
b0 (
b0 '
bx &
b10000000000000000000000000000011 %
1$
b0 #
0"
b0 !
$end
#5000
1"
#10000
0"
#15000
1"
#20000
0"
#25000
1"
#30000
0"
#35000
b0 &
0$
1"
#40000
0"
#45000
b10111011100000 <
b1011101110000000000000000000 =
b1011101110000000000000000000 4
b10111011100000 #
b10111011100000 '
b10111011100000 +
b1 &
1"
#50000
0"
#55000
b10111011100000 O
b1011101110000000000000000000 P
b1011101110000000000000000000 G
b10101101001111 <
b1010110100111100000000000000 =
b1010110100111100000000000000 4
b10111011100000 :
b10111011100000 7
b10111011100000 (
b10111011100000 9
b10111011100000 >
b10101101001111 #
b10101101001111 '
b10101101001111 +
b10 &
1"
#60000
0"
#65000
b10101101001111 O
b1010110100111100000000000000 P
b1010110100111100000000000000 G
b1111001001000101 <
b11111111100100100010100000000000000 =
b11110100010010000000000000000000 6
b1000010010010100000000000000 4
b10111011100000 M
b10111011100000 J
b10111011100000 !
b10111011100000 )
b10111011100000 L
b10101101001111 :
b10111011100000 ;
b10101101001111 7
b10111011100000 8
b10101101001111 (
b10101101001111 9
b10101101001111 >
b10000100100101 #
b10000100100101 '
b10000100100101 +
b11 &
1"
#70000
0"
#75000
b1100001101100101 O
b11111110000110110010100000000000000 P
b11110100010010000000000000000000 I
b11111100100100010100000000000000 G
b1110011010100001 <
b11111111001101010000100000000000000 =
b11110101001011000100000000000000 6
b100011111000000000000000000 4
b1111001001000101 :
b10101101001111 ;
b10000100100101 7
b10101101001111 8
b1111001001000101 (
b1111001001000101 9
b1111001001000101 >
b10101101001111 M
b10111011100000 N
b10101101001111 J
b10111011100000 K
b10101101001111 !
b10101101001111 )
b10101101001111 L
b1000111110000 #
b1000111110000 '
b1000111110000 +
b100 &
1"
#80000
0"
#85000
b1011101101010010 O
b11111101110110101001000000000000000 P
b11110101001011000100000000000000 I
b11111001101010000100000000000000 G
b1101111011011011 <
b11111110111101101101100000000000000 =
b11110111101101101100000000000000 6
b0 4
b1100001101100101 M
b10101101001111 N
b1111001001000101 J
b10101101001111 K
b1100001101100101 !
b1100001101100101 )
b1100001101100101 L
b1110011010100001 :
b1111001001000101 ;
b1000111110000 7
b10000100100101 8
b1110011010100001 (
b1110011010100001 9
b1110011010100001 >
b0 #
b0 '
b0 +
b101 &
1"
#90000
0"
#95000
b1110110010010110 O
b11111111011001001011000000000000000 P
b11011011101100000000000000 I
b11110111101101101100000000000000 G
b1101110000100000 <
b11111110111000010000000000000000000 =
b11111011100001000000000000000000 6
b11111011100001000000000000000000 4
b1101111011011011 :
b1110011010100001 ;
b0 7
b1000111110000 8
b1101111011011011 (
b1101111011011011 9
b1101111011011011 >
b1011101101010010 M
b1100001101100101 N
b1110011010100001 J
b1111001001000101 K
b1011101101010010 !
b1011101101010010 )
b1011101101010010 L
b1110111000010000 #
b1110111000010000 '
b1110111000010000 +
b110 &
1"
#100000
0"
#105000
b1111010101111111 O
b11111111101010111111100000000000000 P
b110010101111100000000000000 I
b11110111000010000000000000000000 G
b1101111011011011 <
b11111110111101101101100000000000000 =
b0 6
b11110111101101101100000000000000 4
b1110110010010110 M
b1011101101010010 N
b1101111011011011 J
b1110011010100001 K
b1110110010010110 !
b1110110010010110 )
b1110110010010110 L
b1101110000100000 :
b1101111011011011 ;
b1110111000010000 7
b0 8
b1101110000100000 (
b1101110000100000 9
b1101110000100000 >
b1101111011011011 #
b1101111011011011 '
b1101111011011011 +
b111 &
1"
#110000
0"
#115000
b0 O
b0 P
b1000010010010100000000000000 I
b11110111101101101100000000000000 G
b1110011010100001 <
b11111111001101010000100000000000000 =
b100011111000000000000000000 6
b11110101001011000100000000000000 4
b1101111011011011 :
b1101110000100000 ;
b1101111011011011 7
b1110111000010000 8
b1101111011011011 (
b1101111011011011 9
b1101111011011011 >
b1111010101111111 M
b1110110010010110 N
b1101110000100000 J
b1101111011011011 K
b1111010101111111 !
b1111010101111111 )
b1111010101111111 L
b1101010010110001 #
b1101010010110001 '
b1101010010110001 +
b1000 &
1"
#120000
0"
#125000
b101010000001 O
b10101000000100000000000000 P
b1000111110000000000000000000 I
b11111001101010000100000000000000 G
b1111001001000101 <
b11111111100100100010100000000000000 =
b1000010010010100000000000000 6
b11110100010010000000000000000000 4
b0 M
b1111010101111111 N
b1101111011011011 J
b1101110000100000 K
b0 !
b0 )
b0 L
b1110011010100001 :
b1101111011011011 ;
b1101010010110001 7
b1101111011011011 8
b1110011010100001 (
b1110011010100001 9
b1110011010100001 >
b1101000100100000 #
b1101000100100000 '
b1101000100100000 +
b1001 &
1"
#130000
0"
#135000
b1001101101010 O
b100110110101000000000000000 P
b1000010010010100000000000000 I
b11111100100100010100000000000000 G
b0 <
b0 =
b1010110100111100000000000000 6
b11110101001011000100000000000000 4
b1111001001000101 :
b1110011010100001 ;
b1101000100100000 7
b1101010010110001 8
b1111001001000101 (
b1111001001000101 9
b1111001001000101 >
b101010000001 M
b0 N
b1110011010100001 J
b1101111011011011 K
b101010000001 !
b101010000001 )
b101010000001 L
b1101010010110001 #
b1101010010110001 '
b1101010010110001 +
b1010 &
1"
#140000
0"
#145000
b1100101011111 O
b110010101111100000000000000 P
b110010101111100000000000000 I
b0 G
b110110111011 <
b11011011101100000000000000 =
b1011101110000000000000000000 6
b11110111101101101100000000000000 4
b1001101101010 M
b101010000001 N
b1111001001000101 J
b1110011010100001 K
b1001101101010 !
b1001101101010 )
b1001101101010 L
b0 :
b1111001001000101 ;
b1101010010110001 7
b1101000100100000 8
b0 (
b0 9
b0 >
b1101111011011011 #
b1101111011011011 '
b1101111011011011 +
b1011 &
1"
#150000
0"
#155000
b1101101110110 O
b110110111011000000000000000 P
b11011011101100000000000000 I
b11011011101100000000000000 G
b1100101011111 <
b110010101111100000000000000 =
b1010110100111100000000000000 6
b11111011100001000000000000000000 4
b110110111011 :
b0 ;
b1101111011011011 7
b1101010010110001 8
b110110111011 (
b110110111011 9
b110110111011 >
b1100101011111 M
b1001101101010 N
b0 J
b1111001001000101 K
b1100101011111 !
b1100101011111 )
b1100101011111 L
b1110111000010000 #
b1110111000010000 '
b1110111000010000 +
b1100 &
1"
#160000
0"
#165000
b1100101011111 O
b110010101111100000000000000 P
b0 I
b110010101111100000000000000 G
b10000100100101 <
b1000010010010100000000000000 =
b1000010010010100000000000000 6
b0 4
b1101101110110 M
b1100101011111 N
b110110111011 J
b0 K
b1101101110110 !
b1101101110110 )
b1101101110110 L
b1100101011111 :
b110110111011 ;
b1110111000010000 7
b1101111011011011 8
b1100101011111 (
b1100101011111 9
b1100101011111 >
b0 #
b0 '
b0 +
b1101 &
1"
#170000
0"
#175000
b1001101101010 O
b100110110101000000000000000 P
b11111100100100010100000000000000 I
b1000010010010100000000000000 G
b10001111100000 <
b1000111110000000000000000000 =
b100011111000000000000000000 6
b100011111000000000000000000 4
b10000100100101 :
b1100101011111 ;
b0 7
b1110111000010000 8
b10000100100101 (
b10000100100101 9
b10000100100101 >
b1100101011111 M
b1101101110110 N
b1100101011111 J
b110110111011 K
b1100101011111 !
b1100101011111 )
b1100101011111 L
b1000111110000 #
b1000111110000 '
b1000111110000 +
b1110 &
1"
#180000
0"
#185000
b101010000001 O
b10101000000100000000000000 P
b11111001101010000100000000000000 I
b1000111110000000000000000000 G
b10000100100101 <
b1000010010010100000000000000 =
b0 6
b1000010010010100000000000000 4
b1001101101010 M
b1100101011111 N
b10000100100101 J
b1100101011111 K
b1001101101010 !
b1001101101010 )
b1001101101010 L
b10001111100000 :
b10000100100101 ;
b1000111110000 7
b0 8
b10001111100000 (
b10001111100000 9
b10001111100000 >
b10000100100101 #
b10000100100101 '
b10000100100101 +
b1111 &
1"
#190000
0"
#195000
b0 O
b0 P
b11110111101101101100000000000000 I
b1000010010010100000000000000 G
b1100101011111 <
b110010101111100000000000000 =
b11111011100001000000000000000000 6
b1010110100111100000000000000 4
b10000100100101 :
b10001111100000 ;
b10000100100101 7
b1000111110000 8
b10000100100101 (
b10000100100101 9
b10000100100101 >
b101010000001 M
b1001101101010 N
b10001111100000 J
b10000100100101 K
b101010000001 !
b101010000001 )
b101010000001 L
b10101101001111 #
b10101101001111 '
b10101101001111 +
b10000 &
1"
#200000
0"
#205000
b1111010101111111 O
b11111111101010111111100000000000000 P
b11110111000010000000000000000000 I
b110010101111100000000000000 G
b110110111011 <
b11011011101100000000000000 =
b11110111101101101100000000000000 6
b1011101110000000000000000000 4
b0 M
b101010000001 N
b10000100100101 J
b10001111100000 K
b0 !
b0 )
b0 L
b1100101011111 :
b10000100100101 ;
b10101101001111 7
b10000100100101 8
b1100101011111 (
b1100101011111 9
b1100101011111 >
b10111011100000 #
b10111011100000 '
b10111011100000 +
b10001 &
1"
#210000
0"
#215000
b1110110010010110 O
b11111111011001001011000000000000000 P
b11110111101101101100000000000000 I
b11011011101100000000000000 G
b0 <
b0 =
b11110101001011000100000000000000 6
b1010110100111100000000000000 4
b110110111011 :
b1100101011111 ;
b10111011100000 7
b10101101001111 8
b110110111011 (
b110110111011 9
b110110111011 >
b1111010101111111 M
b0 N
b1100101011111 J
b10000100100101 K
b1111010101111111 !
b1111010101111111 )
b1111010101111111 L
b10101101001111 #
b10101101001111 '
b10101101001111 +
b10010 &
1"
#220000
0"
#225000
b1110011010100001 O
b11111111001101010000100000000000000 P
b11111001101010000100000000000000 I
b0 G
b1111001001000101 <
b11111111100100100010100000000000000 =
b11110100010010000000000000000000 6
b1000010010010100000000000000 4
b1110110010010110 M
b1111010101111111 N
b110110111011 J
b1100101011111 K
b1110110010010110 !
b1110110010010110 )
b1110110010010110 L
b0 :
b110110111011 ;
b10101101001111 7
b10111011100000 8
b0 (
b0 9
b0 >
b10000100100101 #
b10000100100101 '
b10000100100101 +
b10011 &
1"
#230000
0"
#235000
b1110010010001010 O
b11111111001001000101000000000000000 P
b11111100100100010100000000000000 I
b11111100100100010100000000000000 G
b1110011010100001 <
b11111111001101010000100000000000000 =
b11110101001011000100000000000000 6
b100011111000000000000000000 4
b1111001001000101 :
b0 ;
b10000100100101 7
b10101101001111 8
b1111001001000101 (
b1111001001000101 9
b1111001001000101 >
b1110011010100001 M
b1110110010010110 N
b0 J
b110110111011 K
b1110011010100001 !
b1110011010100001 )
b1110011010100001 L
b1000111110000 #
b1000111110000 '
b1000111110000 +
b10100 &
1"
#240000
0"
#245000
b1110011010100001 O
b11111111001101010000100000000000000 P
b0 I
b11111001101010000100000000000000 G
b1101111011011011 <
b11111110111101101101100000000000000 =
b11110111101101101100000000000000 6
b0 4
b1110010010001010 M
b1110011010100001 N
b1111001001000101 J
b0 K
b1110010010001010 !
b1110010010001010 )
b1110010010001010 L
b1110011010100001 :
b1111001001000101 ;
b1000111110000 7
b10000100100101 8
b1110011010100001 (
b1110011010100001 9
b1110011010100001 >
b0 #
b0 '
b0 +
b10101 &
1"
#250000
0"
#255000
b1110110010010110 O
b11111111011001001011000000000000000 P
b11011011101100000000000000 I
b11110111101101101100000000000000 G
b1101110000100000 <
b11111110111000010000000000000000000 =
b11111011100001000000000000000000 6
b11111011100001000000000000000000 4
b1101111011011011 :
b1110011010100001 ;
b0 7
b1000111110000 8
b1101111011011011 (
b1101111011011011 9
b1101111011011011 >
b1110011010100001 M
b1110010010001010 N
b1110011010100001 J
b1111001001000101 K
b1110011010100001 !
b1110011010100001 )
b1110011010100001 L
b1110111000010000 #
b1110111000010000 '
b1110111000010000 +
b10110 &
1"
#260000
0"
#265000
b1111010101111111 O
b11111111101010111111100000000000000 P
b110010101111100000000000000 I
b11110111000010000000000000000000 G
b1101111011011011 <
b11111110111101101101100000000000000 =
b0 6
b11110111101101101100000000000000 4
b1110110010010110 M
b1110011010100001 N
b1101111011011011 J
b1110011010100001 K
b1110110010010110 !
b1110110010010110 )
b1110110010010110 L
b1101110000100000 :
b1101111011011011 ;
b1110111000010000 7
b0 8
b1101110000100000 (
b1101110000100000 9
b1101110000100000 >
b1101111011011011 #
b1101111011011011 '
b1101111011011011 +
b10111 &
1"
#270000
0"
#275000
b0 O
b0 P
b1000010010010100000000000000 I
b11110111101101101100000000000000 G
b1110011010100001 <
b11111111001101010000100000000000000 =
b100011111000000000000000000 6
b11110101001011000100000000000000 4
b1101111011011011 :
b1101110000100000 ;
b1101111011011011 7
b1110111000010000 8
b1101111011011011 (
b1101111011011011 9
b1101111011011011 >
b1111010101111111 M
b1110110010010110 N
b1101110000100000 J
b1101111011011011 K
b1111010101111111 !
b1111010101111111 )
b1111010101111111 L
b1101010010110001 #
b1101010010110001 '
b1101010010110001 +
b11000 &
1"
#280000
0"
#285000
b101010000001 O
b10101000000100000000000000 P
b1000111110000000000000000000 I
b11111001101010000100000000000000 G
b1111001001000101 <
b11111111100100100010100000000000000 =
b1000010010010100000000000000 6
b11110100010010000000000000000000 4
b0 M
b1111010101111111 N
b1101111011011011 J
b1101110000100000 K
b0 !
b0 )
b0 L
b1110011010100001 :
b1101111011011011 ;
b1101010010110001 7
b1101111011011011 8
b1110011010100001 (
b1110011010100001 9
b1110011010100001 >
b1101000100100000 #
b1101000100100000 '
b1101000100100000 +
b11001 &
1"
#290000
0"
#295000
b1001101101010 O
b100110110101000000000000000 P
b1000010010010100000000000000 I
b11111100100100010100000000000000 G
b0 <
b0 =
b1010110100111100000000000000 6
b11110101001011000100000000000000 4
b1111001001000101 :
b1110011010100001 ;
b1101000100100000 7
b1101010010110001 8
b1111001001000101 (
b1111001001000101 9
b1111001001000101 >
b101010000001 M
b0 N
b1110011010100001 J
b1101111011011011 K
b101010000001 !
b101010000001 )
b101010000001 L
b1101010010110001 #
b1101010010110001 '
b1101010010110001 +
b11010 &
1"
#300000
0"
#305000
b1100101011111 O
b110010101111100000000000000 P
b110010101111100000000000000 I
b0 G
b110110111011 <
b11011011101100000000000000 =
b1011101110000000000000000000 6
b11110111101101101100000000000000 4
b1001101101010 M
b101010000001 N
b1111001001000101 J
b1110011010100001 K
b1001101101010 !
b1001101101010 )
b1001101101010 L
b0 :
b1111001001000101 ;
b1101010010110001 7
b1101000100100000 8
b0 (
b0 9
b0 >
b1101111011011011 #
b1101111011011011 '
b1101111011011011 +
b11011 &
1"
#310000
0"
#315000
b1101101110110 O
b110110111011000000000000000 P
b11011011101100000000000000 I
b11011011101100000000000000 G
b1100101011111 <
b110010101111100000000000000 =
b1010110100111100000000000000 6
b11111011100001000000000000000000 4
b110110111011 :
b0 ;
b1101111011011011 7
b1101010010110001 8
b110110111011 (
b110110111011 9
b110110111011 >
b1100101011111 M
b1001101101010 N
b0 J
b1111001001000101 K
b1100101011111 !
b1100101011111 )
b1100101011111 L
b1110111000010000 #
b1110111000010000 '
b1110111000010000 +
b11100 &
1"
#320000
0"
#325000
b1100101011111 O
b110010101111100000000000000 P
b0 I
b110010101111100000000000000 G
b10000100100101 <
b1000010010010100000000000000 =
b1000010010010100000000000000 6
b0 4
b1101101110110 M
b1100101011111 N
b110110111011 J
b0 K
b1101101110110 !
b1101101110110 )
b1101101110110 L
b1100101011111 :
b110110111011 ;
b1110111000010000 7
b1101111011011011 8
b1100101011111 (
b1100101011111 9
b1100101011111 >
b0 #
b0 '
b0 +
b11101 &
1"
#330000
0"
#335000
b1001101101010 O
b100110110101000000000000000 P
b11111100100100010100000000000000 I
b1000010010010100000000000000 G
b10001111100000 <
b1000111110000000000000000000 =
b100011111000000000000000000 6
b100011111000000000000000000 4
b10000100100101 :
b1100101011111 ;
b0 7
b1110111000010000 8
b10000100100101 (
b10000100100101 9
b10000100100101 >
b1100101011111 M
b1101101110110 N
b1100101011111 J
b110110111011 K
b1100101011111 !
b1100101011111 )
b1100101011111 L
b1000111110000 #
b1000111110000 '
b1000111110000 +
b11110 &
1"
#340000
0"
#345000
b101010000001 O
b10101000000100000000000000 P
b11111001101010000100000000000000 I
b1000111110000000000000000000 G
b10000100100101 <
b1000010010010100000000000000 =
b0 6
b1000010010010100000000000000 4
b1001101101010 M
b1100101011111 N
b10000100100101 J
b1100101011111 K
b1001101101010 !
b1001101101010 )
b1001101101010 L
b10001111100000 :
b10000100100101 ;
b1000111110000 7
b0 8
b10001111100000 (
b10001111100000 9
b10001111100000 >
b10000100100101 #
b10000100100101 '
b10000100100101 +
b11111 &
1"
#350000
0"
#355000
b0 O
b0 P
b11110111101101101100000000000000 I
b1000010010010100000000000000 G
b1100101011111 <
b110010101111100000000000000 =
b11111011100001000000000000000000 6
b1010110100111100000000000000 4
b10000100100101 :
b10001111100000 ;
b10000100100101 7
b1000111110000 8
b10000100100101 (
b10000100100101 9
b10000100100101 >
b101010000001 M
b1001101101010 N
b10001111100000 J
b10000100100101 K
b101010000001 !
b101010000001 )
b101010000001 L
b10101101001111 #
b10101101001111 '
b10101101001111 +
b100000 &
1"
#360000
0"
#365000
b1111010101111111 O
b11111111101010111111100000000000000 P
b11110111000010000000000000000000 I
b110010101111100000000000000 G
b110110111011 <
b11011011101100000000000000 =
b11110111101101101100000000000000 6
b1011101110000000000000000000 4
b0 M
b101010000001 N
b10000100100101 J
b10001111100000 K
b0 !
b0 )
b0 L
b1100101011111 :
b10000100100101 ;
b10101101001111 7
b10000100100101 8
b1100101011111 (
b1100101011111 9
b1100101011111 >
b10111011100000 #
b10111011100000 '
b10111011100000 +
b100001 &
1"
#370000
0"
#375000
b1110110010010110 O
b11111111011001001011000000000000000 P
b11110111101101101100000000000000 I
b11011011101100000000000000 G
b0 <
b0 =
b11110101001011000100000000000000 6
b1010110100111100000000000000 4
b110110111011 :
b1100101011111 ;
b10111011100000 7
b10101101001111 8
b110110111011 (
b110110111011 9
b110110111011 >
b1111010101111111 M
b0 N
b1100101011111 J
b10000100100101 K
b1111010101111111 !
b1111010101111111 )
b1111010101111111 L
b10101101001111 #
b10101101001111 '
b10101101001111 +
b100010 &
1"
#380000
0"
#385000
b1110011010100001 O
b11111111001101010000100000000000000 P
b11111001101010000100000000000000 I
b0 G
b1111001001000101 <
b11111111100100100010100000000000000 =
b11110100010010000000000000000000 6
b1000010010010100000000000000 4
b1110110010010110 M
b1111010101111111 N
b110110111011 J
b1100101011111 K
b1110110010010110 !
b1110110010010110 )
b1110110010010110 L
b0 :
b110110111011 ;
b10101101001111 7
b10111011100000 8
b0 (
b0 9
b0 >
b10000100100101 #
b10000100100101 '
b10000100100101 +
b100011 &
1"
#390000
0"
#395000
b1110010010001010 O
b11111111001001000101000000000000000 P
b11111100100100010100000000000000 I
b11111100100100010100000000000000 G
b1110011010100001 <
b11111111001101010000100000000000000 =
b11110101001011000100000000000000 6
b100011111000000000000000000 4
b1111001001000101 :
b0 ;
b10000100100101 7
b10101101001111 8
b1111001001000101 (
b1111001001000101 9
b1111001001000101 >
b1110011010100001 M
b1110110010010110 N
b0 J
b110110111011 K
b1110011010100001 !
b1110011010100001 )
b1110011010100001 L
b1000111110000 #
b1000111110000 '
b1000111110000 +
b100100 &
1"
#400000
0"
#405000
b1110011010100001 O
b11111111001101010000100000000000000 P
b0 I
b11111001101010000100000000000000 G
b1101111011011011 <
b11111110111101101101100000000000000 =
b11110111101101101100000000000000 6
b0 4
b1110010010001010 M
b1110011010100001 N
b1111001001000101 J
b0 K
b1110010010001010 !
b1110010010001010 )
b1110010010001010 L
b1110011010100001 :
b1111001001000101 ;
b1000111110000 7
b10000100100101 8
b1110011010100001 (
b1110011010100001 9
b1110011010100001 >
b0 #
b0 '
b0 +
b100101 &
1"
#410000
0"
#415000
b1110110010010110 O
b11111111011001001011000000000000000 P
b11011011101100000000000000 I
b11110111101101101100000000000000 G
b1101110000100000 <
b11111110111000010000000000000000000 =
b11111011100001000000000000000000 6
b11111011100001000000000000000000 4
b1101111011011011 :
b1110011010100001 ;
b0 7
b1000111110000 8
b1101111011011011 (
b1101111011011011 9
b1101111011011011 >
b1110011010100001 M
b1110010010001010 N
b1110011010100001 J
b1111001001000101 K
b1110011010100001 !
b1110011010100001 )
b1110011010100001 L
b1110111000010000 #
b1110111000010000 '
b1110111000010000 +
b100110 &
1"
#420000
0"
#425000
b1111010101111111 O
b11111111101010111111100000000000000 P
b110010101111100000000000000 I
b11110111000010000000000000000000 G
b1101111011011011 <
b11111110111101101101100000000000000 =
b0 6
b11110111101101101100000000000000 4
b1110110010010110 M
b1110011010100001 N
b1101111011011011 J
b1110011010100001 K
b1110110010010110 !
b1110110010010110 )
b1110110010010110 L
b1101110000100000 :
b1101111011011011 ;
b1110111000010000 7
b0 8
b1101110000100000 (
b1101110000100000 9
b1101110000100000 >
b1101111011011011 #
b1101111011011011 '
b1101111011011011 +
b100111 &
1"
#430000
0"
#435000
b0 O
b0 P
b1000010010010100000000000000 I
b11110111101101101100000000000000 G
b1110011010100001 <
b11111111001101010000100000000000000 =
b100011111000000000000000000 6
b11110101001011000100000000000000 4
b1101111011011011 :
b1101110000100000 ;
b1101111011011011 7
b1110111000010000 8
b1101111011011011 (
b1101111011011011 9
b1101111011011011 >
b1111010101111111 M
b1110110010010110 N
b1101110000100000 J
b1101111011011011 K
b1111010101111111 !
b1111010101111111 )
b1111010101111111 L
b1101010010110001 #
b1101010010110001 '
b1101010010110001 +
b101000 &
1"
#440000
0"
#445000
b101010000001 O
b10101000000100000000000000 P
b1000111110000000000000000000 I
b11111001101010000100000000000000 G
b1111001001000101 <
b11111111100100100010100000000000000 =
b1000010010010100000000000000 6
b11110100010010000000000000000000 4
b0 M
b1111010101111111 N
b1101111011011011 J
b1101110000100000 K
b0 !
b0 )
b0 L
b1110011010100001 :
b1101111011011011 ;
b1101010010110001 7
b1101111011011011 8
b1110011010100001 (
b1110011010100001 9
b1110011010100001 >
b1101000100100000 #
b1101000100100000 '
b1101000100100000 +
b101001 &
1"
#450000
0"
#455000
b1001101101010 O
b100110110101000000000000000 P
b1000010010010100000000000000 I
b11111100100100010100000000000000 G
b0 <
b0 =
b1010110100111100000000000000 6
b11110101001011000100000000000000 4
b1111001001000101 :
b1110011010100001 ;
b1101000100100000 7
b1101010010110001 8
b1111001001000101 (
b1111001001000101 9
b1111001001000101 >
b101010000001 M
b0 N
b1110011010100001 J
b1101111011011011 K
b101010000001 !
b101010000001 )
b101010000001 L
b1101010010110001 #
b1101010010110001 '
b1101010010110001 +
b101010 &
1"
#460000
0"
#465000
b1100101011111 O
b110010101111100000000000000 P
b110010101111100000000000000 I
b0 G
b110110111011 <
b11011011101100000000000000 =
b1011101110000000000000000000 6
b11110111101101101100000000000000 4
b1001101101010 M
b101010000001 N
b1111001001000101 J
b1110011010100001 K
b1001101101010 !
b1001101101010 )
b1001101101010 L
b0 :
b1111001001000101 ;
b1101010010110001 7
b1101000100100000 8
b0 (
b0 9
b0 >
b1101111011011011 #
b1101111011011011 '
b1101111011011011 +
b101011 &
1"
#470000
0"
