FILTERS/echo/echo.sv
module echo #(
    parameter SAMPLE_WIDTH = 16,
    parameter NUM_ECHO_SAMPLES = 12000
) (
    input logic clk,
    input logic reset,
    input logic signed [SAMPLE_WIDTH-1:0] sample,
    input logic sample_valid,
    output logic signed [SAMPLE_WIDTH-1:0] sample_out
);

  logic [$clog2(NUM_ECHO_SAMPLES)-1:0] count;

  // delay memory
  logic signed [SAMPLE_WIDTH-1:0] arr[0:NUM_ECHO_SAMPLES-1];

  // delayed sample
  logic signed [SAMPLE_WIDTH-1:0] delayed_sample;

  // mixed signal
  logic signed [SAMPLE_WIDTH:0] mixed;

  integer i;

  always_ff @(posedge clk or posedge reset) begin
    if (reset) begin
      count          <= 0;
      delayed_sample <= 0;
      mixed          <= 0;
      sample_out     <= 0;

      for (i = 0; i < NUM_ECHO_SAMPLES; i = i + 1) arr[i] <= 0;

    end else begin
      if (sample_valid) begin
        delayed_sample <= arr[count];

        // current + half delayed
        mixed <= sample + (delayed_sample >>> 1);
        sample_out <= mixed[SAMPLE_WIDTH-1:0];

        // store mixed for repeated echoes
        arr[count] <= mixed[SAMPLE_WIDTH-1:0];

        if (count == NUM_ECHO_SAMPLES - 1) count <= 0;
        else count <= count + 1;
      end
    end
  end

endmodule

FILTERS/echo/testbench.sv
`timescale 1ns/1ps

module tb_echo_cos;

    localparam SAMPLE_WIDTH = 16;
    localparam NUM_ECHO_SAMPLES = 8;

    logic clk;
    logic reset;
    logic signed [SAMPLE_WIDTH-1:0] sample;
    logic sample_valid;
    logic signed [SAMPLE_WIDTH-1:0] sample_out;

    // real variables for cosine
    real t;
    real freq;
    real sample_rate;
    real value;

    integer i;

    echo #(
        .SAMPLE_WIDTH(SAMPLE_WIDTH),
        .NUM_ECHO_SAMPLES(NUM_ECHO_SAMPLES)
    ) dut (
        .clk(clk),
        .reset(reset),
        .sample(sample),
        .sample_valid(sample_valid),
        .sample_out(sample_out)
    );

    // clock
    initial clk = 0;
    always #5 clk = ~clk;

    initial begin
        reset = 1;
        sample = 0;
        sample_valid = 0;

        sample_rate = 48000.0;
        freq = 1000.0;

        repeat(3) @(posedge clk);
        reset = 0;
        sample_valid = 1;

        // test with two impulses
        for(i = 0; i < 200; i++) begin
            @(posedge clk);
            if(i == 0 || i == 100) sample = 10_000;
            else sample = 0;
        end

        sample_valid = 0;
        
        repeat(5) @(posedge clk);
        $finish;
    end

    // print input and output
    always @(posedge clk) begin
        if(sample_valid) begin
            $display("in=%0d, out=%0d", sample, sample_out);
        end
    end

endmodule

VOCAL_EFFECTS/echo/echo_cos.vcd
$date
	Fri Mar 13 00:56:03 2026
$end
$version
	Icarus Verilog
$end
$timescale
	1ps
$end
$scope module tb_echo_cos $end
$var wire 16 ! sample_out [15:0] $end
$var parameter 32 " NUM_ECHO_SAMPLES $end
$var parameter 32 # SAMPLE_WIDTH $end
$var reg 1 $ clk $end
$var reg 1 % reset $end
$var reg 16 & sample [15:0] $end
$var reg 1 ' sample_valid $end
$var real 1 ( freq $end
$var integer 32 ) i [31:0] $end
$var real 1 * sample_rate $end
$var real 1 + t $end
$var real 1 , value $end
$scope module dut $end
$var wire 1 $ clk $end
$var wire 1 % reset $end
$var wire 16 - sample [15:0] $end
$var wire 1 ' sample_valid $end
$var parameter 32 . NUM_ECHO_SAMPLES $end
$var parameter 32 / SAMPLE_WIDTH $end
$var reg 3 0 count [2:0] $end
$var reg 16 1 delayed_sample [15:0] $end
$var reg 17 2 mixed [16:0] $end
$var reg 16 3 sample_out [15:0] $end
$var integer 32 4 i [31:0] $end
$upscope $end
$upscope $end
$enddefinitions $end
$comment Show the parameter values. $end
$dumpall
b10000 /
b1000 .
b10000 #
b1000 "
$end
#0
$dumpvars
b1000 4
b0 3
b0 2
b0 1
b0 0
b0 -
r0 ,
r0 +
r48000 *
bx )
r1000 (
0'
b0 &
1%
0$
b0 !
$end
#5000
b1000 4
1$
#10000
0$
#15000
b1000 4
1$
#20000
0$
#25000
b1 0
b0 )
1'
0%
1$
#30000
0$
#35000
b10 0
b10111011100000 2
b1 )
b10111011100000 &
b10111011100000 -
r1 ,
1$
#40000
0$
#45000
b11 0
b10111011100000 !
b10111011100000 3
b10111001111001 2
b10 )
b10111001111001 &
b10111001111001 -
r0.9914448613933339 ,
r2.083333333333333e-05 +
1$
#50000
0$
#55000
b100 0
b10111001111001 !
b10111001111001 3
b10110101000111 2
b11 )
b10110101000111 &
b10110101000111 -
r0.9659258263664938 ,
r4.166666666666667e-05 +
1$
#60000
0$
#65000
b101 0
b10110101000111 !
b10110101000111 3
b10101101001110 2
b100 )
b10101101001110 &
b10101101001110 -
r0.923879532683006 ,
r6.25e-05 +
1$
#70000
0$
#75000
b110 0
b10101101001110 !
b10101101001110 3
b10100010011000 2
b101 )
b10100010011000 &
b10100010011000 -
r0.8660254040835881 ,
r8.333333333333333e-05 +
1$
#80000
0$
#85000
b111 0
b10100010011000 !
b10100010011000 3
b10010100110000 2
b110 )
b10010100110000 &
b10010100110000 -
r0.7933533407465118 ,
r0.0001041666666666667 +
1$
#90000
0$
#95000
b0 0
b10010100110000 !
b10010100110000 3
b10000100100101 2
b111 )
b10000100100101 &
b10000100100101 -
r0.7071067818211393 ,
r0.000125 +
1$
#100000
0$
#105000
b1 0
b10000100100101 !
b10000100100101 3
b1110010001001 2
b1000 )
b1110010001001 &
b1110010001001 -
r0.6087614298393799 ,
r0.0001458333333333333 +
1$
#110000
0$
#115000
b10 0
b1110010001001 !
b1110010001001 3
b1011101110000 2
b1001 )
b1011101110000 &
b1011101110000 -
r0.5000000010362841 ,
r0.0001666666666666667 +
1$
#120000
0$
#125000
b11 0
b1011101110000 !
b1011101110000 3
b1000111110000 2
b10111011100000 1
b1010 )
b1000111110000 &
b1000111110000 -
r0.3826834336087908 ,
r0.0001875 +
1$
#130000
0$
#135000
b100 0
b1000111110000 !
b1000111110000 3
b10001110010001 2
b10111001111001 1
b1011 )
b110000100001 &
b110000100001 -
r0.2588190465473015 ,
r0.0002083333333333333 +
1$
#140000
0$
#145000
b101 0
b10001110010001 !
b10001110010001 3
b1110101011010 2
b10110101000111 1
b1100 )
b11000011110 &
b11000011110 -
r0.1305261938512977 ,
r0.0002291666666666667 +
1$
#150000
0$
#155000
b110 0
b1110101011010 !
b1110101011010 3
b1011010100011 2
b10101101001110 1
b1101 )
b0 &
b0 -
r1.794896514918784e-09 ,
r0.00025 +
1$
#160000
0$
#165000
b111 0
b1011010100011 !
b1011010100011 3
b111110001001 2
b10100010011000 1
b1110 )
b1111100111100010 &
b1111100111100010 -
r-0.1305261902922153 ,
r0.0002708333333333333 +
1$
#170000
0$
#175000
b0 0
b111110001001 !
b111110001001 3
b100000101011 2
b10010100110000 1
b1111 )
b1111001111011111 &
b1111001111011111 -
r-0.2588190430798277 ,
r0.0002916666666666667 +
1$
#180000
0$
#185000
b1 0
b100000101011 !
b100000101011 3
b10101000 2
b10000100100101 1
b10000 )
b1110111000010000 &
b1110111000010000 -
r-0.3826834302922545 ,
r0.0003125 +
1$
#190000
0$
#195000
b10 0
b10101000 !
b10101000 3
b11111100100100011 2
b1110010001001 1
b10001 )
b1110100010010001 &
b1110100010010001 -
r-0.4999999979274318 ,
r0.0003333333333333333 +
1$
#200000
0$
#205000
b11 0
b1111100100100011 !
b1111100100100011 3
b11111000110111011 2
b1011101110000 1
b10010 )
b1110001101110111 &
b1110001101110111 -
r-0.6087614269914056 ,
r0.0003541666666666667 +
1$
#210000
0$
#215000
b100 0
b1111000110111011 !
b1111000110111011 3
b11110101010010011 2
b1000111110000 1
b10011 )
b1101111011011011 &
b1101111011011011 -
r-0.7071067792827723 ,
r0.000375 +
1$
#220000
0$
#225000
b101 0
b1110101010010011 !
b1110101010010011 3
b11110001111001000 2
b10001110010001 1
b10100 )
b1101101011010000 &
b1101101011010000 -
r-0.793353338561184 ,
r0.0003958333333333333 +
1$
#230000
0$
#235000
b110 0
b1110001111001000 !
b1110001111001000 3
b11110100100110000 2
b1110101011010 1
b10101 )
b1101011101101000 &
b1101011101101000 -
r-0.8660254022886916 ,
r0.0004166666666666667 +
1$
#240000
0$
#245000
b111 0
b1110100100110000 !
b1110100100110000 3
b11110001101011111 2
b1011010100011 1
b10110 )
b1101010010110010 &
b1101010010110010 -
r-0.9238795313092517 ,
r0.0004375 +
1$
#250000
0$
#255000
b0 0
b1110001101011111 !
b1110001101011111 3
b11101111000001010 2
b111110001001 1
b10111 )
b1101001010111001 &
b1101001010111001 -
r-0.9659258254373869 ,
r0.0004583333333333333 +
1$
#260000
0$
#265000
b1 0
b1101111000001010 !
b1101111000001010 3
b11101100101001011 2
b100000101011 1
b11000 )
b1101000110000111 &
b1101000110000111 -
r-0.9914448609247718 ,
r0.0004791666666666666 +
1$
#270000
0$
#275000
b10 0
b1101100101001011 !
b1101100101001011 3
b11101010100110101 2
b10101000 1
b11001 )
b1101000100100000 &
b1101000100100000 -
r-1 ,
r0.0005 +
1$
#280000
0$
#285000
b11 0
b1101010100110101 !
b1101010100110101 3
b11101000111011011 2
b1111100100100011 1
b11010 )
b1101000110000111 &
b1101000110000111 -
r-0.9914448618618958 ,
r0.0005208333333333333 +
1$
#290000
0$
#295000
b100 0
b1101000111011011 !
b1101000111011011 3
b11100111101001010 2
b1111000110111011 1
b11011 )
b1101001010111001 &
b1101001010111001 -
r-0.9659258272956007 ,
r0.0005416666666666666 +
1$
#300000
0$
#305000
b101 0
b1100111101001010 !
b1100111101001010 3
b11100110110001111 2
b1110101010010011 1
b11100 )
b1101010010110010 &
b1101010010110010 -
r-0.9238795340567606 ,
r0.0005625 +
1$
#310000
0$
#315000
b110 0
b1100110110001111 !
b1100110110001111 3
b11100110010110001 2
b1110001111001000 1
b11101 )
b1101011101101000 &
b1101011101101000 -
r-0.8660254058784846 ,
r0.0005833333333333334 +
1$
#320000
0$
#325000
b111 0
b1100110010110001 !
b1100110010110001 3
b11100110010110100 2
b1110100100110000 1
b11110 )
b1101101011010000 &
b1101101011010000 -
r-0.7933533429318393 ,
r0.0006041666666666667 +
1$
#330000
0$
#335000
b0 0
b1100110010110100 !
b1100110010110100 3
b11101001101110011 2
b1110001101011111 1
b11111 )
b1101111011011011 &
b1101111011011011 -
r-0.7071067843595064 ,
r0.000625 +
1$
#340000
0$
#345000
b1 0
b1101001101110011 !
b1101001101110011 3
b11101010100100110 2
b1101111000001010 1
b100000 )
b1110001101110111 &
b1110001101110111 -
r-0.6087614326873545 ,
r0.0006458333333333333 +
1$
#350000
0$
#355000
b10 0
b1101010100100110 !
b1101010100100110 3
b11101011110010101 2
b1101100101001011 1
b100001 )
b1110100010010000 &
b1110100010010000 -
r-0.5000000041451365 ,
r0.0006666666666666666 +
1$
#360000
0$
#365000
b11 0
b1101011110010101 !
b1101011110010101 3
b11101101010110101 2
b1101010100110101 1
b100010 )
b1110111000010000 &
b1110111000010000 -
r-0.3826834369253277 ,
r0.0006875 +
1$
#370000
0$
#375000
b100 0
b1101101010110101 !
b1101101010110101 3
b11101111001111001 2
b1101000111011011 1
b100011 )
b1111001111011111 &
b1111001111011111 -
r-0.2588190500147751 ,
r0.0007083333333333334 +
1$
#380000
0$
#385000
b101 0
b1101111001111001 !
b1101111001111001 3
b11110001011001111 2
b1100111101001010 1
b100100 )
b1111100111100010 &
b1111100111100010 -
r-0.130526197410379 ,
r0.0007291666666666667 +
1$
#390000
0$
#395000
b110 0
b1110001011001111 !
b1110001011001111 3
b11110011110100101 2
b1100110110001111 1
b100101 )
b0 &
b0 -
r-5.384689322711746e-09 ,
r0.00075 +
1$
#400000
0$
#405000
b111 0
b1110011110100101 !
b1110011110100101 3
b11110110011100101 2
b1100110010110001 1
b100110 )
b11000011110 &
b11000011110 -
r0.130526186733133 ,
r0.0007708333333333333 +
1$
#410000
0$
#415000
b0 0
b1110110011100101 !
b1110110011100101 3
b11111001001111001 2
b1100110010110100 1
b100111 )
b110000100001 &
b110000100001 -
r0.2588190396123533 ,
r0.0007916666666666666 +
1$
#420000
0$
#425000
b1 0
b1111001001111001 !
b1111001001111001 3
b11111100001001010 2
b1101001101110011 1
b101000 )
b1000111110000 &
b1000111110000 -
r0.3826834269757176 ,
r0.0008125 +
1$
#430000
0$
#435000
b10 0
b1111100001001010 !
b1111100001001010 3
b100101000 2
b1101010100100110 1
b101001 )
b1011101101111 &
b1011101101111 -
r0.4999999948185802 ,
r0.0008333333333333334 +
1$
#440000
0$
#445000
b11 0
b100101000 !
b100101000 3
b11100011100 2
b1101011110010101 1
b101010 )
b1110010001001 &
b1110010001001 -
r0.6087614241434313 ,
r0.0008541666666666667 +
1$
#450000
0$
#455000
b100 0
b11100011100 !
b11100011100 3
b110011101111 2
b1101101010110101 1
b101011 )
b10000100100101 &
b10000100100101 -
r0.7071067767444054 ,
r0.000875 +
1$
#460000
0$
#465000
b101 0
b110011101111 !
b110011101111 3
b1001010001010 2
b1101111001111001 1
b101100 )
b10010100110000 &
b10010100110000 -
r0.7933533363758567 ,
r0.0008958333333333333 +
1$
#470000
0$
#475000
b110 0
b1001010001010 !
b1001010001010 3
b1011111010100 2
b1110001011001111 1
b101101 )
b10100010011000 &
b10100010011000 -
r0.8660254004937946 ,
r0.0009166666666666666 +
1$
#480000
0$
#485000
b111 0
b1011111010100 !
b1011111010100 3
b1110010110101 2
b1110011110100101 1
b101110 )
b10101101001110 &
b10101101001110 -
r0.923879529935497 ,
r0.0009375 +
1$
#490000
0$
#495000
b0 0
b1110010110101 !
b1110010110101 3
b10000100011001 2
b1110110011100101 1
b101111 )
b10110101000111 &
b10110101000111 -
r0.96592582450828 ,
r0.0009583333333333333 +
1$
#500000
0$
#505000
b1 0
b10000100011001 !
b10000100011001 3
b10010011101011 2
b1111001001111001 1
b110000 )
b10111001111001 &
b10111001111001 -
r0.9914448604562096 ,
r0.0009791666666666666 +
1$
#510000
0$
#515000
b10 0
b10010011101011 !
b10010011101011 3
b10100000011100 2
b1111100001001010 1
b110001 )
b10111011100000 &
b10111011100000 -
r1 ,
r0.001 +
1$
#520000
0$
#525000
b11 0
b10100000011100 !
b10100000011100 3
b10101010011110 2
b100101000 1
b110010 )
b10111001111001 &
b10111001111001 -
r0.9914448623304579 ,
r0.001020833333333333 +
1$
#530000
0$
#535000
b100 0
b10101010011110 !
b10101010011110 3
b10110111011011 2
b11100011100 1
b110011 )
b10110101000111 &
b10110101000111 -
r0.9659258282247074 ,
r0.001041666666666667 +
1$
#540000
0$
#545000
b101 0
b10110111011011 !
b10110111011011 3
b10111011011100 2
b110011101111 1
b110100 )
b10101101001110 &
b10101101001110 -
r0.9238795354305147 ,
r0.0010625 +
1$
#550000
0$
#555000
b110 0
b10111011011100 !
b10111011011100 3
b10111100001111 2
b1001010001010 1
b110101 )
b10100010011000 &
b10100010011000 -
r0.8660254076733815 ,
r0.001083333333333333 +
1$
#560000
0$
#565000
b111 0
b10111100001111 !
b10111100001111 3
b10111001110101 2
b1011111010100 1
b110110 )
b10010100110000 &
b10010100110000 -
r0.7933533451171668 ,
r0.001104166666666667 +
1$
#570000
0$
#575000
b0 0
b10111001110101 !
b10111001110101 3
b10110100001111 2
b1110010110101 1
b110111 )
b10000100100101 &
b10000100100101 -
r0.707106786897874 ,
r0.001125 +
1$
#580000
0$
#585000
b1 0
b10110100001111 !
b10110100001111 3
b10101011100011 2
b10000100011001 1
b111000 )
b1110010001001 &
b1110010001001 -
r0.6087614355353285 ,
r0.001145833333333333 +
1$
#590000
0$
#595000
b10 0
b10101011100011 !
b10101011100011 3
b10011111111100 2
b10010011101011 1
b111001 )
b1011101110000 &
b1011101110000 -
r0.500000007253988 ,
r0.001166666666666667 +
1$
#600000
0$
#605000
b11 0
b10011111111100 !
b10011111111100 3
b10010001100101 2
b10100000011100 1
b111010 )
b1000111110000 &
b1000111110000 -
r0.3826834402418636 ,
r0.0011875 +
1$
#610000
0$
#615000
b100 0
b10010001100101 !
b10010001100101 3
b10000000101111 2
b10101010011110 1
b111011 )
b110000100001 &
b110000100001 -
r0.2588190534822493 ,
r0.001208333333333333 +
1$
#620000
0$
#625000
b101 0
b10000000101111 !
b10000000101111 3
b1101101101101 2
b10110111011011 1
b111100 )
b11000011110 &
b11000011110 -
r0.1305262009694622 ,
r0.001229166666666667 +
1$
#630000
0$
#635000
b110 0
b1101101101101 !
b1101101101101 3
b1011011101101 2
b10111011011100 1
b111101 )
b0 &
b0 -
r8.974482796638523e-09 ,
r0.00125 +
1$
#640000
0$
#645000
b111 0
b1011011101101 !
b1011011101101 3
b1000101010000 2
b10111100001111 1
b111110 )
b1111100111100010 &
b1111100111100010 -
r-0.1305261831740508 ,
r0.001270833333333333 +
1$
#650000
0$
#655000
b0 0
b1000101010000 !
b1000101010000 3
b101101100110 2
b10111001110101 1
b111111 )
b1111001111011111 &
b1111001111011111 -
r-0.258819036144879 ,
r0.001291666666666667 +
1$
#660000
0$
#665000
b1 0
b101101100110 !
b101101100110 3
b10101001010 2
b10110100001111 1
b1000000 )
b1110111000010000 &
b1110111000010000 -
r-0.3826834236591817 ,
r0.0013125 +
1$
#670000
0$
#675000
b10 0
b10101001010 !
b10101001010 3
b11111111100011000 2
b10101011100011 1
b1000001 )
b1110100010010001 &
b1110100010010001 -
r-0.4999999917097271 ,
r0.001333333333333333 +
1$
#680000
0$
#685000
b11 0
b1111111100011000 !
b1111111100011000 3
b11111100011101000 2
b10011111111100 1
b1000010 )
b1110001101110111 &
b1110001101110111 -
r-0.6087614212954566 ,
r0.001354166666666667 +
1$
#690000
0$
#695000
b100 0
b1111100011101000 !
b1111100011101000 3
b11111001011011001 2
b10010001100101 1
b1000011 )
b1101111011011011 &
b1101111011011011 -
r-0.7071067742060374 ,
r0.001375 +
1$
#700000
0$
#705000
b101 0
b1111001011011001 !
b1111001011011001 3
b11110110100000010 2
b10000000101111 1
b1000100 )
b1101101011010000 &
b1101101011010000 -
r-0.7933533341905289 ,
r0.001395833333333333 +
1$
#710000
0$
#715000
b110 0
b1110110100000010 !
b1110110100000010 3
b11110011101111111 2
b1101101101101 1
b1000101 )
b1101011101101000 &
b1101011101101000 -
r-0.8660253986988987 ,
r0.001416666666666667 +
1$
#720000
0$
#725000
b111 0
b1110011101111111 !
b1110011101111111 3
b11110001001101000 2
b1011011101101 1
b1000110 )
b1101010010110010 &
b1101010010110010 -
r-0.9238795285617429 ,
r0.0014375 +
1$
#730000
0$
#735000
b0 0
b1110001001101000 !
b1110001001101000 3
b11101111000101111 2
b1000101010000 1
b1000111 )
b1101001010111001 &
b1101001010111001 -
r-0.9659258235791736 ,
r0.001458333333333333 +
1$
#740000
0$
#745000
b1 0
b1101111000101111 !
b1101111000101111 3
b11101101000101111 2
b101101100110 1
b1001000 )
b1101000110000111 &
b1101000110000111 -
r-0.9914448599876476 ,
r0.001479166666666667 +
1$
#750000
0$
#755000
b10 0
b1101101000101111 !
b1101101000101111 3
b11101011011010100 2
b10101001010 1
b1001001 )
b1101000100100001 &
b1101000100100001 -
r-0.9999999999999999 ,
r0.0015 +
1$
#760000
0$
#765000
b11 0
b1101011011010100 !
b1101011011010100 3
b11101010000101100 2
b1111111100011000 1
b1001010 )
b1101000110000111 &
b1101000110000111 -
r-0.9914448627990199 ,
r0.001520833333333333 +
1$
#770000
0$
#775000
b100 0
b1101010000101100 !
b1101010000101100 3
b11101001001000101 2
b1111100011101000 1
b1001011 )
b1101001010111001 &
b1101001010111001 -
r-0.9659258291538145 ,
r0.001541666666666667 +
1$
#780000
0$
#785000
b101 0
b1101001001000101 !
b1101001001000101 3
b11101000100100110 2
b1111001011011001 1
b1001100 )
b1101010010110010 &
b1101010010110010 -
r-0.9238795368042692 ,
r0.0015625 +
1$
#790000
0$
#795000
b110 0
b1101000100100110 !
b1101000100100110 3
b11101000011010100 2
b1110110100000010 1
b1001101 )
b1101011101101000 &
b1101011101101000 -
r-0.8660254094682782 ,
r0.001583333333333333 +
1$
#800000
0$
#805000
b111 0
b1101000011010100 !
b1101000011010100 3
b11101000101010001 2
b1110011101111111 1
b1001110 )
b1101101011010000 &
b1101101011010000 -
r-0.7933533473024946 ,
r0.001604166666666667 +
1$
#810000
0$
#815000
b0 0
b1101000101010001 !
b1101000101010001 3
b11101001010011010 2
b1110001001101000 1
b1001111 )
b1101111011011011 &
b1101111011011011 -
r-0.7071067894362413 ,
r0.001625 +
1$
#820000
0$
#825000
b1 0
b1101001010011010 !
b1101001010011010 3
b11101010010101011 2
b1101111000101111 1
b1010000 )
b1110001101110111 &
b1110001101110111 -
r-0.6087614383833031 ,
r0.001645833333333333 +
1$
#830000
0$
#835000
b10 0
b1101010010101011 !
b1101010010101011 3
b11101011110100111 2
b1101101000101111 1
b1010001 )
b1110100010010000 &
b1110100010010000 -
r-0.5000000103628396 ,
r0.001666666666666667 +
1$
#840000
0$
#845000
b11 0
b1101011110100111 !
b1101011110100111 3
b11101101100100111 2
b1101011011010100 1
b1010010 )
b1110111000010000 &
b1110111000010000 -
r-0.3826834435584003 ,
r0.0016875 +
1$
#850000
0$
#855000
b100 0
b1101101100100111 !
b1101101100100111 3
b11101111101001001 2
b1101010000101100 1
b1010011 )
b1111001111011111 &
b1111001111011111 -
r-0.2588190569497226 ,
r0.001708333333333333 +
1$
#860000
0$
#865000
b101 0
b1101111101001001 !
b1101111101001001 3
b11110001111111000 2
b1101001001000101 1
b1010100 )
b1111100111100010 &
b1111100111100010 -
r-0.1305262045285436 ,
r0.001729166666666667 +
1$
#870000
0$
#875000
b110 0
b1110001111111000 !
b1110001111111000 3
b11110100100100010 2
b1101000100100110 1
b1010101 )
b0 &
b0 -
r-1.256427538238688e-08 ,
r0.00175 +
1$
#880000
0$
#885000
b111 0
b1110100100100010 !
b1110100100100010 3
b11110111010110001 2
b1101000011010100 1
b1010110 )
b11000011110 &
b11000011110 -
r0.1305261796149693 ,
r0.001770833333333333 +
1$
#890000
0$
#895000
b0 0
b1110111010110001 !
b1110111010110001 3
b11111010010001011 2
b1101000101010001 1
b1010111 )
b110000100001 &
b110000100001 -
r0.2588190326774065 ,
r0.001791666666666667 +
1$
#900000
0$
#905000
b1 0
b1111010010001011 !
b1111010010001011 3
b11111101010011000 2
b1101001010011010 1
b1011000 )
b1000111110000 &
b1000111110000 -
r0.382683420342645 ,
r0.0018125 +
1$
#910000
0$
#915000
b10 0
b1111101010011000 !
b1111101010011000 3
b10111100 2
b1101010010101011 1
b1011001 )
b1011101101111 &
b1011101101111 -
r0.4999999886008747 ,
r0.001833333333333333 +
1$
#920000
0$
#925000
b11 0
b10111100 !
b10111100 3
b11011011110 2
b1101011110100111 1
b1011010 )
b1110010001001 &
b1110010001001 -
r0.608761418447482 ,
r0.001854166666666667 +
1$
#930000
0$
#935000
b100 0
b11011011110 !
b11011011110 3
b110011111000 2
b1101101100100111 1
b1011011 )
b10000100100101 &
b10000100100101 -
r0.7071067716676701 ,
r0.001875 +
1$
#940000
0$
#945000
b101 0
b110011111000 !
b110011111000 3
b1001011000011 2
b1101111101001001 1
b1011100 )
b10010100110000 &
b10010100110000 -
r0.7933533320052011 ,
r0.001895833333333333 +
1$
#950000
0$
#955000
b110 0
b1001011000011 !
b1001011000011 3
b1100000111100 2
b1110001111111000 1
b1011101 )
b10100010011000 &
b10100010011000 -
r0.866025396904001 ,
r0.001916666666666667 +
1$
#960000
0$
#965000
b111 0
b1100000111100 !
b1100000111100 3
b1110101001010 2
b1110100100100010 1
b1011110 )
b10101101001110 &
b10101101001110 -
r0.9238795271879884 ,
r0.0019375 +
1$
#970000
0$
#975000
b0 0
b1110101001010 !
b1110101001010 3
b10000111011000 2
b1110111010110001 1
b1011111 )
b10110101000111 &
b10110101000111 -
r0.9659258226500661 ,
r0.001958333333333333 +
1$
#980000
0$
#985000
b1 0
b10000111011000 !
b10000111011000 3
b10010111010001 2
b1111010010001011 1
b1100000 )
b10111001111001 &
b10111001111001 -
r0.9914448595190858 ,
r0.001979166666666667 +
1$
#990000
0$
#995000
b10 0
b10010111010001 !
b10010111010001 3
b10100100100100 2
b1111101010011000 1
b1100001 )
b10111011011111 &
b10111011011111 -
r0.9999999999999999 ,
r0.002 +
1$
#1000000
0$
#1005000
b11 0
b10100100100100 !
b10100100100100 3
b10101111000101 2
b10111100 1
b1100010 )
b10111001111001 &
b10111001111001 -
r0.9914448632675819 ,
r0.002020833333333333 +
1$
#1010000
0$
#1015000
b100 0
b10101111000101 !
b10101111000101 3
b10110110100101 2
b11011011110 1
b1100011 )
b10110101000111 &
b10110101000111 -
r0.9659258300829214 ,
r0.002041666666666666 +
1$
#1020000
0$
#1025000
b101 0
b10110110100101 !
b10110110100101 3
b10111010111101 2
b110011111000 1
b1100100 )
b10101101001110 &
b10101101001110 -
r0.9238795381780229 ,
r0.0020625 +
1$
#1030000
0$
#1035000
b110 0
b10111010111101 !
b10111010111101 3
b10111100010100 2
b1001011000011 1
b1100101 )
b10100010011000 &
b10100010011000 -
r0.8660254112631741 ,
r0.002083333333333333 +
1$
#1040000
0$
#1045000
b111 0
b10111100010100 !
b10111100010100 3
b10111010010001 2
b1100000111100 1
b1100110 )
b10010100110000 &
b10010100110000 -
r0.7933533494878224 ,
r0.002104166666666667 +
1$
#1050000
0$
#1055000
b0 0
b10111010010001 !
b10111010010001 3
b10110101000011 2
b1110101001010 1
b1100111 )
b10000100100101 &
b10000100100101 -
r0.7071067919746072 ,
r0.002125 +
1$
#1060000
0$
#1065000
b1 0
b10110101000011 !
b10110101000011 3
b10101100101110 2
b10000111011000 1
b1101000 )
b1110010001001 &
b1110010001001 -
r0.6087614412312777 ,
r0.002145833333333333 +
1$
#1070000
0$
#1075000
b10 0
b10101100101110 !
b10101100101110 3
b10100001011100 2
b10010111010001 1
b1101001 )
b1011101110000 &
b1011101110000 -
r0.5000000134716934 ,
r0.002166666666666667 +
1$
#1080000
0$
#1085000
b11 0
b10100001011100 !
b10100001011100 3
b10010011011000 2
b10100100100100 1
b1101010 )
b1000111110000 &
b1000111110000 -
r0.3826834468749354 ,
r0.0021875 +
1$
#1090000
0$
#1095000
b100 0
b10010011011000 !
b10010011011000 3
b10000010110011 2
b10101111000101 1
b1101011 )
b110000100001 &
b110000100001 -
r0.2588190604171969 ,
r0.002208333333333333 +
1$
#1100000
0$
#1105000
b101 0
b10000010110011 !
b10000010110011 3
b1110000000000 2
b10110110100101 1
b1101100 )
b11000011110 &
b11000011110 -
r0.1305262080876259 ,
r0.002229166666666667 +
1$
#1110000
0$
#1115000
b110 0
b1110000000000 !
b1110000000000 3
b1011011010010 2
b10111010111101 1
b1101101 )
b0 &
b0 -
r1.61540706326705e-08 ,
r0.00225 +
1$
#1120000
0$
#1125000
b111 0
b1011011010010 !
b1011011010010 3
b1000101000000 2
b10111100010100 1
b1101110 )
b1111100111100010 &
b1111100111100010 -
r-0.1305261760558888 ,
r0.002270833333333333 +
1$
#1130000
0$
#1135000
b0 0
b1000101000000 !
b1000101000000 3
b101101101001 2
b10111010010001 1
b1101111 )
b1111001111011111 &
b1111001111011111 -
r-0.2588190292099322 ,
r0.002291666666666667 +
1$
#1140000
0$
#1145000
b1 0
b101101101001 !
b101101101001 3
b10101011000 2
b10110101000011 1
b1110000 )
b1110111000010000 &
b1110111000010000 -
r-0.3826834170261083 ,
r0.0023125 +
1$
#1150000
0$
#1155000
b10 0
b10101011000 !
b10101011000 3
b11111111100110010 2
b10101100101110 1
b1110001 )
b1110100010010001 &
b1110100010010001 -
r-0.4999999854920238 ,
r0.002333333333333334 +
1$
#1160000
0$
#1165000
b11 0
b1111111100110010 !
b1111111100110010 3
b11111100100001110 2
b10100001011100 1
b1110010 )
b1110001101110111 &
b1110001101110111 -
r-0.6087614155995074 ,
r0.002354166666666667 +
1$
#1170000
0$
#1175000
b100 0
b1111100100001110 !
b1111100100001110 3
b11111001100001001 2
b10010011011000 1
b1110011 )
b1101111011011011 &
b1101111011011011 -
r-0.7071067691293039 ,
r0.002375 +
1$
#1180000
0$
#1185000
b101 0
b1111001100001001 !
b1111001100001001 3
b11110110100111100 2
b10000010110011 1
b1110100 )
b1101101011010000 &
b1101101011010000 -
r-0.7933533298198732 ,
r0.002395833333333333 +
1$
#1190000
0$
#1195000
b110 0
b1110110100111100 !
b1110110100111100 3
b11110011111000001 2
b1110000000000 1
b1110101 )
b1101011101101000 &
b1101011101101000 -
r-0.8660253951091051 ,
r0.002416666666666667 +
1$
#1200000
0$
#1205000
b111 0
b1110011111000001 !
b1110011111000001 3
b11110001010110010 2
b1011011010010 1
b1110110 )
b1101010010110010 &
b1101010010110010 -
r-0.9238795258142338 ,
r0.0024375 +
1$
#1210000
0$
#1215000
b0 0
b1110001010110010 !
b1110001010110010 3
b11101111000100010 2
b1000101000000 1
b1110111 )
b1101001010111001 &
b1101001010111001 -
r-0.9659258217209591 ,
r0.002458333333333333 +
1$
#1220000
0$
#1225000
b1 0
b1101111000100010 !
b1101111000100010 3
b11101101000100111 2
b101101101001 1
b1111000 )
b1101000110000111 &
b1101000110000111 -
r-0.9914448590505237 ,
r0.002479166666666667 +
1$
#1230000
0$
#1235000
b10 0
b1101101000100111 !
b1101101000100111 3
b11101011011010101 2
b10101011000 1
b1111001 )
b1101000100100001 &
b1101000100100001 -
r-0.9999999999999999 ,
r0.0025 +
1$
#1240000
0$
#1245000
b11 0
b1101011011010101 !
b1101011011010101 3
b11101010000110011 2
b1111111100110010 1
b1111010 )
b1101000110000111 &
b1101000110000111 -
r-0.9914448637361439 ,
r0.002520833333333333 +
1$
#1250000
0$
#1255000
b100 0
b1101010000110011 !
b1101010000110011 3
b11101001001010010 2
b1111100100001110 1
b1111011 )
b1101001010111001 &
b1101001010111001 -
r-0.9659258310120283 ,
r0.002541666666666666 +
1$
#1260000
0$
